Workbook

Sheet F&I Log
T1: Total VSC | U1: Triton Protect Advantage | V1: Total MAINTENANCE | W1: Triton Image Guard | X1: 3 For 1 | Y1: Triton Drive 360 | Z1: Lease Wear Care | AA1: Lease EWT | AB1: Other Aftermarket
A2: Contract Date | B2: VIN | C2: Year | D2: Make | E2: Model | F2: Vehicle Type | G2: Contract Type | H2: Customer | I2: Sale Type | J2: First Name | K2: Last Name | L2: Address1 | M2: City | N2: State | O2: Zip | P2: Email Address | Q2: Home Phone | R2: Work Phone | S2: Cell Phone | T2: Income | U2: Income | V2: Income | W2: Income | X2: Income | Y2: Income | Z2: Income | AA2: Income | AB2: Income
A3: 2025-01-02 | B3: 1FMCU9MN7RUB00853 | C3: 2024 | D3: FORD | E3: ESCAPE | F3: Truck | G3: Retail | H3: BILL WISE'S EXCAVATING INC | I3: Conventional | K3: BILL WISE'S EXCAVATING INC | L3: 944 JOLLYTOWN RD | M3: NEW FREEPORT | N3: PA | O3: 15352-1574 | Q3: 724-451-8175 | T3: 600 | U3: 0 | V3: 0 | W3: 0 | X3: 0 | Y3: 0 | Z3: 0 | AA3: 0 | AB3: 0
A4: 2025-01-02 | B4: 1FMUK8KH9SGA60104 | C4: 2025 | D4: FORD | E4: EXPLORER | F4: Truck | G4: Retail | H4: HAYES,DEBORAH | I4: Conventional | J4: DEBORAH | K4: HAYES | L4: 106 GERTRUDE DR | M4: CHALFONT | N4: PA | O4: 18914 | P4: DHAYES1020@GMAIL.COM | Q4: 215-272-2654 | S4: 215-272-2654 | T4: 1801 | U4: 0 | V4: 405 | W4: 0 | X4: 0 | Y4: 0 | Z4: 0 | AA4: 0 | AB4: 0
A5: 2025-01-02 | B5: 1FMUK8DH1SGA43276 | C5: 2025 | D5: FORD | E5: EXPLORER | F5: Truck | G5: Retail | H5: BASZNIANIN,DARIUSZ | I5: Conventional | J5: DARIUSZ | K5: BASZNIANIN | L5: 1469 TARLETON PL | M5: WARMINSTER | N5: PA | O5: 18974 | P5: DBDARlUSZ@GMAIL.COM | Q5: 215-403-1125 | S5: 215-403-1124 | T5: 0 | U5: 0 | V5: 0 | W5: 0 | X5: 0 | Y5: 0 | Z5: 0 | AA5: 0 | AB5: 0
A6: 2025-01-02 | B6: 3FMTK3SU8RMA43287 | C6: 2024 | D6: FORD | E6: MUSTME | F6: Truck | G6: Retail | H6: POIRIER,LUC STEPHANE | I6: Conventional | J6: LUC | K6: POIRIER | L6: 113 TELEGRAPH RD | M6: PERKASIE | N6: PA | O6: 18944-2644 | P6: LUC.S.POIRIER@GMAIL.COM | Q6: 612-434-4486 | S6: 612-434-4486 | T6: 1280 | U6: 0 | V6: 405 | W6: 0 | X6: 0 | Y6: 653 | Z6: 0 | AA6: 0 | AB6: 0
A7: 2025-01-02 | B7: 3FMTK3SU3RMA52687 | C7: 2024 | D7: FORD | E7: MUSTME | F7: Truck | G7: Retail | H7: THALJI,REEMA KHALID | I7: Conventional | J7: REEMA | K7: THALJI | L7: 608 LAKEVIEW CT | M7: KNG OF PRUSSA | N7: PA | O7: 19406-1542 | P7: REEMA.THALJI@GMAIL.COM | Q7: 734-904-5470 | S7: 734-904-5470 | T7: 0 | U7: 0 | V7: 0 | W7: 0 | X7: 0 | Y7: 0 | Z7: 0 | AA7: 0 | AB7: 0
A8: 2025-01-02 | B8: 1FMCU9MN9RUA35522 | C8: 2024 | D8: FORD | E8: ESCAPE | F8: Truck | G8: Retail | H8: BILL WISE'S EXCAVATING INC | I8: Conventional | K8: BILL WISE'S EXCAVATING INC | L8: 944 JOLLYTOWN RD | M8: NEW FREEPORT | N8: PA | O8: 15352-1574 | Q8: 724-451-8175 | T8: 400 | U8: 0 | V8: 0 | W8: 0 | X8: 0 | Y8: 0 | Z8: 0 | AA8: 0 | AB8: 0
A9: 2025-01-02 | B9: 1FMCU9MN7RUA78790 | C9: 2024 | D9: FORD | E9: ESCAPE | F9: Truck | G9: Lease | H9: KWIATKOWSKI,GARY | I9: Conventional | J9: GARY | K9: KWIATKOWSKI | L9: 1333 CLEARVIEW DR | M9: JAMISON | N9: PA | O9: 18929-1149 | Q9: 215-262-4614 | S9: 215-262-4614 | T9: 0 | U9: 0 | V9: 0 | W9: 0 | X9: 0 | Y9: 25 | Z9: 0 | AA9: 0 | AB9: 0
A10: 2025-01-02 | B10: 1FDNF7AN0SDF09472 | C10: 2025 | D10: FORD MEDIUM TRUCKS | E10: F-750 | F10: Truck | G10: Retail | H10: DAIDONE ELECTRIC, INC | I10: Fleet | K10: DAIDONE ELECTRIC, INC | L10: 200 RAYMOND BLVD | M10: NEWARK | N10: NJ | O10: 07105-4608 | P10: NRIBEIRO@DAIDONEELECTRIC.COM | Q10: 973-332-8173 | R10: 973-332-8173 | S10: 973-332-8173 | T10: 0 | U10: 0 | V10: 0 | W10: 0 | X10: 0 | Y10: 0 | Z10: 0 | AA10: 0 | AB10: 0
A11: 2025-01-02 | B11: 1FTFW7LD3SFA04379 | C11: 2025 | D11: FORD | E11: F-150 HYBRID | F11: Truck | G11: Retail | H11: PARK,JOON HYONG | I11: Conventional | J11: JOON | K11: PARK | L11: 419 FORT HILL CIR | M11: FT WASHINGTON | N11: PA | O11: 19034 | P11: JP@JNJFINANCIAL.PRO | Q11: 267-968-8949 | R11: 267-968-8949 | S11: 267-968-8949 | T11: 1000 | U11: 0 | V11: 295 | W11: 0 | X11: 0 | Y11: 726 | Z11: 0 | AA11: 0 | AB11: 0
A12: 2025-01-02 | B12: 1FDNF7AN6SDF09475 | C12: 2025 | D12: FORD MEDIUM TRUCKS | E12: F-750 | F12: Truck | G12: Retail | H12: DAIDONE ELECTRIC, INC | I12: Fleet | K12: DAIDONE ELECTRIC, INC | L12: 200 RAYMOND BLVD | M12: NEWARK | N12: NJ | O12: 07105-4608 | P12: NRIBEIRO@DAIDONEELECTRIC.COM | Q12: 973-332-8173 | R12: 973-332-8173 | S12: 973-332-8173 | T12: 0 | U12: 0 | V12: 0 | W12: 0 | X12: 0 | Y12: 0 | Z12: 0 | AA12: 0 | AB12: 0
A13: 2025-01-02 | B13: 1FT8W3BN9SEC06449 | C13: 2025 | D13: FORD | E13: F-350 | F13: Truck | G13: Retail | H13: BRAVERMAN,CRAIG BRIAN | I13: Conventional | J13: CRAIG | K13: BRAVERMAN | L13: 410 SCHOOL ST PO BOX 1423 | M13: NORTH WALES | N13: PA | O13: 19454 | P13: CBRAVERMAN@COMCAST.NET | Q13: 215-275-0011 | R13: 215-275-0011 | T13: 0 | U13: 0 | V13: 0 | W13: 0 | X13: 0 | Y13: 0 | Z13: 0 | AA13: 0 | AB13: 0
A14: 2025-01-02 | B14: 2FMPK4J94RBB23644 | C14: 2024 | D14: FORD | E14: EDGE | F14: Truck | G14: Retail | H14: CONVILLE,PATRICK F | I14: Conventional | J14: PATRICK | K14: CONVILLE | L14: 1034 WESTON WAY | M14: HATFIELD | N14: PA | O14: 19440-2985 | P14: PATRICK.F.CONVILLE@GMAIL.COM | Q14: 215-840-2124 | R14: 215-840-0115 | S14: 215-840-0115 | T14: 0 | U14: 0 | V14: 0 | W14: 0 | X14: 0 | Y14: 0 | Z14: 0 | AA14: 0 | AB14: 0
A15: 2025-01-02 | B15: 1FMCU9GN2RUA64355 | C15: 2024 | D15: FORD | E15: ESCAPE | F15: Truck | G15: Retail | H15: BILL WISE'S EXCAVATING INC | I15: Conventional | K15: BILL WISE'S EXCAVATING INC | L15: 944 JOLLYTOWN RD | M15: NEW FREEPORT | N15: PA | O15: 15352-1574 | Q15: 724-451-8175 | T15: 600 | U15: 0 | V15: 0 | W15: 0 | X15: 0 | Y15: 0 | Z15: 0 | AA15: 0 | AB15: 0
A16: 2025-01-02 | B16: 1FMWK8HC3SGB00858 | C16: 2025 | D16: FORD | E16: EXP | F16: Truck | G16: Retail | H16: CASTIMORE,RICHARD G | I16: Conventional | J16: RICHARD | K16: CASTIMORE | L16: 103 LINABERRY RD | M16: COLUMBIA | N16: NJ | O16: 07832-2309 | P16: MBCASTIMORE@GMAIL.COM | Q16: 908-459-4360 | S16: 908-619-0140 | T16: 1500 | U16: 0 | V16: 0 | W16: 0 | X16: 0 | Y16: 431 | Z16: 0 | AA16: 0 | AB16: 0
A17: 2025-01-02 | B17: 1FT8W3DM4SEC05536 | C17: 2025 | D17: FORD | E17: F-350 | F17: Truck | G17: Retail | H17: MURPHY IV,WILLIAM HOUSTON | I17: Conventional | J17: WILLIAM | K17: MURPHY | L17: 414 GLENWAY RD | M17: GLENSIDE | N17: PA | O17: 19038-7020 | P17: billy414@aol.com | Q17: 215-778-9074 | T17: 100 | U17: 0 | V17: 0 | W17: 0 | X17: 0 | Y17: 0 | Z17: 0 | AA17: 0 | AB17: 0
A18: 2025-01-02 | B18: 1FMDE7BH1RLB50110 | C18: 2024 | D18: FORD | E18: BRONCO | F18: Truck | G18: Lease | H18: MISCIO,LINDSAY | I18: Conventional | J18: LINDSAY | K18: MISCIO | L18: 4959 JULIE COURT | M18: DOYLESTOWN | N18: PA | O18: 18902 | P18: LINDSAYMISCIO@GMAIL.COM | Q18: 215-850-5776 | S18: 215-771-4646 | T18: 0 | U18: 0 | V18: 0 | W18: 0 | X18: 0 | Y18: 0 | Z18: 0 | AA18: 0 | AB18: 0
A19: 2025-01-02 | B19: 1FMCU9GN7RUB50230 | C19: 2024 | D19: FORD | E19: ESCAPE | F19: Truck | G19: Retail | H19: BILL WISE'S EXCAVATING INC | I19: Conventional | K19: BILL WISE'S EXCAVATING INC | L19: 944 JOLLYTOWN RD | M19: NEW FREEPORT | N19: PA | O19: 15352-1574 | Q19: 724-451-8175 | T19: 600 | U19: 0 | V19: 0 | W19: 0 | X19: 0 | Y19: 0 | Z19: 0 | AA19: 0 | AB19: 0
A20: 2025-01-02 | B20: 1FMUK8KH7SGA37114 | C20: 2025 | D20: FORD | E20: EXPLORER | F20: Truck | G20: Retail | H20: WAHRHAFTIG,JOEL F | I20: Conventional | J20: JOEL | K20: WAHRHAFTIG | L20: 202 SHEPARD LN | M20: CHALFONT | N20: PA | O20: 18914-3569 | P20: JFWTECHIE@GMAIL.COM | Q20: 267-475-5561 | S20: 267-475-5561 | T20: 0 | U20: 0 | V20: 0 | W20: 0 | X20: 0 | Y20: 0 | Z20: 0 | AA20: 0 | AB20: 0
A21: 2025-01-02 | B21: 1FTVW3L71RWG04035 | C21: 2024 | D21: FORD | E21: F-150 | F21: Truck | G21: Retail | H21: RICKENS JR,ALBERT JOHN | I21: Conventional | J21: ALBERT | K21: RICKENS | L21: 725 BRIDGTON PIKE | M21: MANTUA | N21: NJ | O21: 08051 | P21: AJSTOYS63@GMAIL.COM | Q21: 609-238-1679 | R21: 609-238-1679 | S21: 609-238-1679 | T21: 0 | U21: 0 | V21: 0 | W21: 0 | X21: 0 | Y21: 0 | Z21: 0 | AA21: 0 | AB21: 0
A22: 2025-01-02 | B22: 1FTER4PH2RLE73909 | C22: 2024 | D22: FORD | E22: RANGER | F22: Truck | G22: Retail | H22: MATERIAL SOLUTIONS INC | I22: Conventional | K22: MATERIAL SOLUTIONS INC | L22: 28C INDUSTRIAL DR | M22: TRENTON | N22: NJ | O22: 08619-3245 | P22: MUSTANGROG06@ICLOUD.COM | Q22: 215-801-1452 | S22: 215-801-1452 | T22: 0 | U22: 0 | V22: 0 | W22: 0 | X22: 0 | Y22: 0 | Z22: 0 | AA22: 0 | AB22: 0
A23: 2025-01-02 | B23: 1FMUK8DH8SGA36549 | C23: 2025 | D23: FORD | E23: EXPLORER | F23: Truck | G23: Lease | H23: GAMBONE,JOHN MICHAEL | I23: Conventional | J23: JOHN | K23: GAMBONE | L23: 202 RED MAPLE CT | M23: CHALFONT | N23: PA | O23: 18914-4413 | P23: JGAMBONE424@GMAIL.COM | Q23: 215-206-6758 | S23: 215-206-6758 | T23: 0 | U23: 0 | V23: 0 | W23: 0 | X23: 0 | Y23: 431 | Z23: 0 | AA23: 0 | AB23: 0
A24: 2025-01-03 | B24: 1FMUK8KH9SGB01556 | C24: 2025 | D24: FORD | E24: EXP | F24: Truck | G24: Lease | H24: LOLAS II,WILLIAM | I24: Conventional | J24: WILLIAM | K24: LOLAS II | L24: 2030 BEDFORDSHIRE RD | M24: FURLONG | N24: PA | O24: 18925 | P24: BLOLAS@COMCAST.NET | Q24: 215-805-3290 | R24: 215-805-3290 | S24: 215-805-3290 | T24: 0 | U24: 0 | V24: 0 | W24: 0 | X24: 0 | Y24: 0 | Z24: 0 | AA24: 0 | AB24: 0
A25: 2025-01-03 | B25: 1FMDE8BH0RLA90116 | C25: 2024 | D25: FORD | E25: BRONCO | F25: Truck | G25: Retail | H25: WETHERILL,JULIE LYNN | I25: Conventional | J25: JULIE | K25: WETHERILL | L25: 2115 UPPER STUMP RD | M25: FOUNTAINVILLE | N25: PA | O25: 18923 | P25: DKWETHERILL@GMAIL.COM | Q25: 267-429-5700 | S25: 267-429-5700 | T25: 0 | U25: 0 | V25: 0 | W25: 0 | X25: 0 | Y25: 0 | Z25: 0 | AA25: 0 | AB25: 0
A26: 2025-01-04 | B26: 1FMDE2AP4RLA32533 | C26: 2024 | D26: FORD | E26: BRONCO | F26: Truck | G26: Retail | H26: SYLVESTER,JOHN | I26: Conventional | J26: JOHN | K26: SYLVESTER | L26: 1410 BENNER SCHOOL RD | M26: QUAKERTOWN | N26: PA | O26: 18951 | P26: HIPWR308@VERIZON.NET | Q26: 267-372-0641 | R26: 267-372-0641 | T26: 0 | U26: 0 | V26: 0 | W26: 0 | X26: 0 | Y26: 0 | Z26: 0 | AA26: 0 | AB26: 0
A27: 2025-01-04 | B27: 1FMCU9NZ3SUA36883 | C27: 2025 | D27: FORD | E27: ESCAPE | F27: Truck | G27: Retail | H27: ARMAGOST,JOHN ROBERT | I27: Conventional | J27: JOHN | K27: ARMAGOST | L27: 4804 WOODSPRING DR | M27: PIPERSVILLE | N27: PA | O27: 18947-1064 | P27: ARMAGOSTJACK@GMAIL.COM | Q27: 267-337-5854 | S27: 267-337-5854 | T27: 1945 | U27: 0 | V27: 120 | W27: 0 | X27: 0 | Y27: 726 | Z27: 0 | AA27: 0 | AB27: 0
A28: 2025-01-06 | B28: 1FDRF3FN2PEC92687 | C28: 2023 | D28: FORD | E28: F-350 | F28: Truck | G28: Retail | H28: INTEK AUTO LEASING | I28: Fleet | K28: INTEK AUTO LEASING | L28: 152 EAGLE ROCK AVE | M28: ROSELAND | N28: NJ | O28: 07068-1320 | Q28: 973-403-7788 | R28: 973-403-7788 | S28: 484-226-9523 | T28: 0 | U28: 0 | V28: 0 | W28: 0 | X28: 0 | Y28: 0 | Z28: 0 | AA28: 0 | AB28: 0
A29: 2025-01-07 | B29: 1FM5K8AW1SGA86667 | C29: 2025 | D29: FORD | E29: EXPLORER | F29: Truck | G29: Retail | H29: BOROUGH OF CONSHOHOCKEN | I29: Fleet | K29: BOROUGH OF CONSHOHOCKEN | L29: 4000 FAYETTE STREET SUITE 200 | M29: CONSHOHOCKEN | N29: PA | O29: 19428-2187 | P29: PCOSTA@CONSHOCKENPA.GOV | Q29: 610-828-4031 | S29: 610-476-8396 | T29: 0 | U29: 0 | V29: 0 | W29: 0 | X29: 0 | Y29: 0 | Z29: 0 | AA29: 0 | AB29: 0
A30: 2025-01-07 | B30: 1FT8W2BN1REE83522 | C30: 2024 | D30: FORD | E30: F-250 | F30: Truck | G30: Retail | H30: FISHER,SCOTT GORDON | I30: Conventional | J30: SCOTT | K30: FISHER | L30: 105 JANE CHAPMAN DR | M30: NEWTOWN | N30: PA | O30: 18940-3123 | P30: FISHERHARDWARE@AOL.COM | Q30: 215-550-6257 | R30: 215-350-9345 | S30: 215-350-9345 | T30: 0 | U30: 0 | V30: 0 | W30: 0 | X30: 0 | Y30: 431 | Z30: 0 | AA30: 0 | AB30: 0
A31: 2025-01-07 | B31: 1FMEE9BP6RLB14579 | C31: 2024 | D31: FORD | E31: BRONCO | F31: Truck | G31: Retail | H31: FIERABEND,DAVID FREDERICK | I31: Conventional | J31: DAVID | K31: FIERABEND | L31: 6390 FLEECYDALE RD | M31: CARVERSVILLE | N31: PA | O31: 18913 | Q31: 609-240-5262 | S31: 609-240-5262 | T31: 0 | U31: 0 | V31: 0 | W31: 0 | X31: 0 | Y31: 0 | Z31: 0 | AA31: 0 | AB31: 0
A32: 2025-01-07 | B32: 1FMEE2BP4RLB14913 | C32: 2024 | D32: FORD | E32: BRONCO | F32: Truck | G32: Retail | H32: HARRISON,MATTHEW THOMAS | I32: Conventional | J32: MATTHEW | K32: HARRISON | L32: 648 BENNETT LN | M32: PERKASIE | N32: PA | O32: 18944-2609 | P32: HARRISON9128@GMAIL.COM | Q32: 814-574-9800 | R32: 814-574-9800 | S32: 814-574-9800 | T32: 0 | U32: 0 | V32: 0 | W32: 0 | X32: 0 | Y32: 0 | Z32: 0 | AA32: 0 | AB32: 0
A33: 2025-01-07 | B33: 1FDTF4HT8PDA08069 | C33: 2023 | D33: FORD | E33: F-450 | F33: Truck | G33: Retail | H33: BOROUGH OF DANVILLE | I33: Fleet | K33: BOROUGH OF DANVILLE | L33: 463 MILL ST | M33: DANVILLE | N33: PA | O33: 17821-1012 | Q33: 570-275-3091 | T33: 0 | U33: 0 | V33: 0 | W33: 0 | X33: 0 | Y33: 0 | Z33: 0 | AA33: 0 | AB33: 0
A34: 2025-01-08 | B34: 1FDUF5HT8RDA10689 | C34: 2024 | D34: FORD | E34: F-550 | F34: Truck | G34: Lease | H34: C&M WASTE WATER SERVICE LLC | I34: Conventional | K34: C&M WASTE WATER SERVICE LLC | L34: 944 JOLLYTOWN RD | M34: NEW FREEPORT | N34: PA | O34: 15352-1574 | Q34: 724-451-8175 | S34: 412-475-0169 | T34: 1350 | U34: 0 | V34: 0 | W34: 0 | X34: 0 | Y34: 0 | Z34: 0 | AA34: 0 | AB34: 0
A35: 2025-01-08 | B35: 1FTBW1Y89RKA35242 | C35: 2024 | D35: FORD | E35: TRANSIT | F35: Truck | G35: Retail | H35: CLEARVIEW WINDOW CLEANING SERVICES, LLC | I35: Conventional | K35: CLEARVIEW WINDOW CLEANING SERVICES, LLC | L35: 2385 LANGHORNE YARDLEY RD | M35: LANGHORNE | N35: PA | O35: 19047 | P35: BRIAN.WINDOWS@GMAIL.COM | Q35: 215-493-2214 | S35: 215-493-2214 | T35: 0 | U35: 0 | V35: 0 | W35: 0 | X35: 0 | Y35: 0 | Z35: 0 | AA35: 0 | AB35: 0
A36: 2025-01-08 | B36: 1FD9X4HT4REC71423 | C36: 2024 | D36: FORD | E36: F-450 | F36: Truck | G36: Lease | H36: C&M WASTE WATER SERVICE LLC | I36: Conventional | K36: C&M WASTE WATER SERVICE LLC | L36: 944 JOLLYTOWN RD | M36: NEW FREEPORT | N36: PA | O36: 15352-1574 | Q36: 724-451-8175 | S36: 412-475-0169 | T36: 1350 | U36: 0 | V36: 0 | W36: 0 | X36: 0 | Y36: 0 | Z36: 0 | AA36: 0 | AB36: 0
A37: 2025-01-08 | B37: 1FBAX2C82RKB47794 | C37: 2024 | D37: FORD | E37: TRANSIT | F37: Truck | G37: Retail | H37: LUZERNE COUNTY TRANSPORTATION AUTHORITY | I37: Fleet | K37: LUZERNE COUNTY TRANSPORTATION AUTHORITY | L37: 315 NORTHAMPTON ST | M37: KINGSTON | N37: PA | O37: 18704-5423 | Q37: 570-288-9356 | T37: 0 | U37: 0 | V37: 0 | W37: 0 | X37: 0 | Y37: 0 | Z37: 0 | AA37: 0 | AB37: 0
A38: 2025-01-09 | B38: 1FMUK8KH6SGA35466 | C38: 2025 | D38: FORD | E38: EXPLORER | F38: Truck | G38: Retail | H38: BRESLIN,CASEY REBECCA | I38: Conventional | J38: CASEY | K38: BRESLIN | L38: 5004 BIRDIE LN | M38: DOYLESTOWN | N38: PA | O38: 18901 | P38: CASEYRBRESLIN@GMAIL.COM | Q38: 610-888-8517 | R38: 215-847-9006 | S38: 610-888-8517 | T38: 2000 | U38: 0 | V38: 0 | W38: 0 | X38: 0 | Y38: 631 | Z38: 0 | AA38: 0 | AB38: 0
A39: 2025-01-11 | B39: 3FTTW8H3XSRA00602 | C39: 2025 | D39: FORD | E39: MAVERICK | F39: Truck | G39: Retail | H39: PCM CONTRACTING INC | I39: Conventional | K39: PCM CONTRACTING INC | L39: 537 E COUNTY LINE RD | M39: HATBORO | N39: PA | O39: 19040-1217 | Q39: 215-400-1073 | T39: 0 | U39: 0 | V39: 0 | W39: 0 | X39: 0 | Y39: 0 | Z39: 0 | AA39: 0 | AB39: 0
A40: 2025-01-11 | B40: 1FMCU9MN4RUA67908 | C40: 2024 | D40: FORD | E40: ESCAPE | F40: Truck | G40: Lease | H40: HAINES,WAYNE G | I40: Conventional | J40: WAYNE | K40: HAINES | L40: 83 ARISTOTLE WAY | M40: CRANBURY | N40: NJ | O40: 08512 | P40: WGHAINES60@VERIZON.NET | Q40: 609-448-3019 | R40: 215-787-2234 | S40: 347-413-3051 | T40: 0 | U40: 0 | V40: 0 | W40: 0 | X40: 0 | Y40: 790 | Z40: 0 | AA40: 0 | AB40: 0
A41: 2025-01-11 | B41: 3FMCR9B60RRF70453 | C41: 2024 | D41: FORD | E41: BRONCO SPORT | F41: Truck | G41: Retail | H41: ANDINO,MICHAEL JASON | I41: Conventional | J41: MICHAEL | K41: ANDINO | L41: 1007 RUNAWAY DR | M41: PENNSBURG | N41: PA | O41: 18073-1650 | P41: BLACKHEART1756@GMAIL.COM | Q41: 267-382-6264 | S41: 267-382-6264 | T41: 1250 | U41: 0 | V41: 0 | W41: 0 | X41: 0 | Y41: 431 | Z41: 0 | AA41: 0 | AB41: 0
A42: 2025-01-11 | B42: 1FTER4HH7RLE68834 | C42: 2024 | D42: FORD | E42: RANGER | F42: Truck | G42: Retail | H42: IPPOLDO,ROBERT JUSTIN | I42: Conventional | J42: ROBERT | K42: IPPOLDO | L42: 3 PLUMRIDGE RD | M42: DOYLESTOWN | N42: PA | O42: 18902-9244 | Q42: 610-209-1010 | S42: 610-209-1010 | T42: 0 | U42: 0 | V42: 0 | W42: 0 | X42: 0 | Y42: 0 | Z42: 0 | AA42: 0 | AB42: 0
A43: 2025-01-11 | B43: 1FMWK8GC4SGB00885 | C43: 2025 | D43: FORD | E43: EXP | F43: Truck | G43: Retail | H43: NACEVILLE MATERIALS JOINT VENTURE | I43: Conventional | K43: NACEVILLE MATERIALS JOINT VENTURE | L43: 350 S MAIN ST STE 207 | M43: DOYLESTOWN | N43: PA | O43: 18901 | P43: BMILLER@MILLERSONPAVING.COM | Q43: 267-880-2422 | R43: 267-880-2422 | S43: 215-416-4055 | T43: 0 | U43: 0 | V43: 0 | W43: 0 | X43: 0 | Y43: 0 | Z43: 0 | AA43: 0 | AB43: 0
A44: 2025-01-13 | B44: 1FTMF1LP5RKF05046 | C44: 2024 | D44: FORD | E44: F-150 | F44: Truck | G44: Retail | H44: FISHERS TRUE VALUE HARDWARE | I44: Conventional | K44: FISHERS TRUE VALUE HARDWARE | L44: 5790 EASTON RD | M44: PLUMSTEADVILLE | N44: PA | O44: 18949 | P44: fisherhardware@aol.com | Q44: 215-350-9345 | R44: 215-766-8220 | T44: 0 | U44: 0 | V44: 0 | W44: 0 | X44: 0 | Y44: 0 | Z44: 0 | AA44: 0 | AB44: 0
A45: 2025-01-13 | B45: 1FTBF2AA0REF25571 | C45: 2024 | D45: FORD | E45: F-250 | F45: Truck | G45: Retail | H45: PKF MARK III INC | I45: Conventional | K45: PKF MARK III INC | L45: 17 BLACK SMITH RD | M45: NEWTOWN | N45: PA | O45: 18940-1877 | P45: jmb@pkfm.com | Q45: 215-968-5031 | R45: 610-770-7940 | S45: 215-478-7653 | T45: 0 | U45: 0 | V45: 0 | W45: 0 | X45: 0 | Y45: 0 | Z45: 0 | AA45: 0 | AB45: 0
A46: 2025-01-13 | B46: 1FMDE7BH3RLB37651 | C46: 2024 | D46: FORD | E46: BRONCO | F46: Truck | G46: Retail | H46: RUBIN,JENNIFER | I46: Conventional | J46: JENNIFER | K46: RUBIN | L46: 165 POLO DR | M46: NORTH WALES | N46: PA | O46: 19454-4273 | P46: jennifer.rubin@att.net | Q46: 215-264-5514 | S46: 215-264-5514 | T46: 1500 | U46: 0 | V46: 0 | W46: 0 | X46: 0 | Y46: 431 | Z46: 0 | AA46: 0 | AB46: 0
A47: 2025-01-13 | B47: 1FTFW3L88RKF73712 | C47: 2024 | D47: FORD | E47: F-150 | F47: Truck | G47: Retail | H47: EUREKA STONE QUARRY, INC. | I47: Fleet | K47: EUREKA STONE QUARRY, INC. | L47: 851 COUNTY LINE RD | M47: HUNTINGDON VALLEY | N47: PA | O47: 19006 | P47: CA8186@AOL.COM | Q47: 215-716-3185 | S47: 215-651-5231 | T47: 0 | U47: 0 | V47: 0 | W47: 0 | X47: 0 | Y47: 0 | Z47: 0 | AA47: 0 | AB47: 0
A48: 2025-01-13 | B48: 1FTBF2AA7REE47323 | C48: 2024 | D48: FORD | E48: F-250 | F48: Truck | G48: Retail | H48: PKF MARK III INC | I48: Conventional | K48: PKF MARK III INC | L48: 17 BLACK SMITH RD | M48: NEWTOWN | N48: PA | O48: 18940-1877 | P48: jmb@pkfm.com | Q48: 215-968-5031 | R48: 610-770-7940 | S48: 215-478-7653 | T48: 0 | U48: 0 | V48: 0 | W48: 0 | X48: 0 | Y48: 0 | Z48: 0 | AA48: 0 | AB48: 0
A49: 2025-01-14 | B49: 1FDBF8P81RKB22817 | C49: 2024 | D49: FORD | E49: TRANSIT | F49: Truck | G49: Retail | H49: EC SALES LLC | I49: Fleet | K49: EC SALES LLC | L49: 2775 BLUE WATER RD | M49: EAGAN | N49: MN | O49: 55121 | T49: 0 | U49: 0 | V49: 0 | W49: 0 | X49: 0 | Y49: 0 | Z49: 0 | AA49: 0 | AB49: 0
A50: 2025-01-14 | B50: 1FTBR1Y84RKA20056 | C50: 2024 | D50: FORD | E50: TRANSIT | F50: Truck | G50: Retail | H50: LEGACY DOOR COMPANY | I50: Conventional | K50: LEGACY DOOR COMPANY | L50: 480 SCHOOL LN STE 200 | M50: HARLEYSVILLE | N50: PA | O50: 19438-4318 | T50: 0 | U50: 0 | V50: 0 | W50: 0 | X50: 0 | Y50: 0 | Z50: 0 | AA50: 0 | AB50: 0
A51: 2025-01-14 | B51: 3FMCR9B63RRF68504 | C51: 2024 | D51: FORD | E51: BRONCO SPORT | F51: Truck | G51: Retail | H51: ROESING JR,TIMOTHY GEORGE | I51: Conventional | J51: TIMOTHY | K51: ROESING | L51: 721 MARIETTA DR | M51: AMBLER | N51: PA | O51: 19002 | P51: TIMROESING@VERIZON.NET | Q51: 267-324-9666 | S51: 267-324-9666 | T51: 0 | U51: 0 | V51: 0 | W51: 0 | X51: 0 | Y51: 0 | Z51: 0 | AA51: 0 | AB51: 0
A52: 2025-01-14 | B52: 1FTBR1C83RKB84776 | C52: 2024 | D52: FORD | E52: TRANSIT | F52: Truck | G52: Retail | H52: UNIVERSAL DOOR SERVICES LLC | I52: Conventional | K52: UNIVERSAL DOOR SERVICES LLC | L52: 480 SCHOOL LN STE 200 | M52: HARLEYSVILLE | N52: PA | O52: 19438 | Q52: 215-256-6776 | R52: 215-256-6776 | T52: 0 | U52: 0 | V52: 0 | W52: 0 | X52: 0 | Y52: 0 | Z52: 0 | AA52: 0 | AB52: 0
A53: 2025-01-14 | B53: 3FTTW8BA0SRA12264 | C53: 2025 | D53: FORD | E53: MAVERICK | F53: Truck | G53: Retail | H53: CENTRAL BUCKS AMBULANCE AND RESCUE | I53: Fleet | K53: CENTRAL BUCKS AMBULANCE AND RESCUE | L53: 455 EAST ST | M53: DOYLESTOWN | N53: PA | O53: 18901-3844 | Q53: 215-348-3343 | S53: 215-778-2949 | T53: 0 | U53: 0 | V53: 0 | W53: 0 | X53: 0 | Y53: 0 | Z53: 0 | AA53: 0 | AB53: 0
A54: 2025-01-14 | B54: 3FMCR9C6XRRF70197 | C54: 2024 | D54: FORD | E54: BRONCO SPORT | F54: Truck | G54: Retail | H54: WADE,RYAN MICHAEL | I54: Conventional | J54: RYAN | K54: WADE | L54: 403 SALMON ST | M54: PHILADELPHIA | N54: PA | O54: 19125-4226 | Q54: 215-510-8484 | R54: 215-510-8484 | S54: 215-510-8484 | T54: 987 | U54: 0 | V54: 0 | W54: 0 | X54: 0 | Y54: 726 | Z54: 0 | AA54: 0 | AB54: 0
A55: 2025-01-14 | B55: 1FDWX7DE0SDF02177 | C55: 2025 | D55: FORD MEDIUM TRUCKS | E55: F-750 | F55: Truck | G55: Retail | H55: TD CONSTRUCTION COMPANY | I55: Conventional | K55: TD CONSTRUCTION COMPANY | L55: 168 CHARLES ST | M55: KNG OF PRUSSA | N55: PA | O55: 19406-2550 | P55: TDCONSTRUCTIONCO@LIVE.COM | Q55: 610-656-7289 | R55: 610-656-7289 | S55: 610-656-7289 | T55: 3500 | U55: 0 | V55: 0 | W55: 0 | X55: 0 | Y55: 0 | Z55: 0 | AA55: 0 | AB55: 0
A56: 2025-01-15 | B56: 1FTBF4UG0PKB24077 | C56: 2023 | D56: FORD | E56: TRANSIT | F56: Truck | G56: Retail | H56: CHEMSTATION PHILADELPHIA LTD | I56: Conventional | K56: CHEMSTATION PHILADELPHIA LTD | L56: 415 BOOT RD STE B | M56: DOWNINGTOWN | N56: PA | O56: 19335-5913 | P56: AHOMAN@CHEMSTATION.COM | Q56: 215-266-4534 | R56: 484-696-1443 | S56: 215-266-4534 | T56: 0 | U56: 0 | V56: 0 | W56: 0 | X56: 0 | Y56: 0 | Z56: 0 | AA56: 0 | AB56: 0
A57: 2025-01-15 | B57: 3FMCR9B6XRRF71173 | C57: 2024 | D57: FORD | E57: BRONCO SPORT | F57: Truck | G57: Lease | H57: GOLDEN,SHANE | I57: Conventional | J57: SHANE | K57: GOLDEN | L57: 781 EVERGREEN CIR | M57: TELFORD | N57: PA | O57: 18969 | P57: SHANEGOLDEN24@YAHOO.COM | Q57: 302-561-5194 | R57: 302-561-5194 | S57: 302-561-5194 | T57: 0 | U57: 0 | V57: 0 | W57: 0 | X57: 0 | Y57: 0 | Z57: 0 | AA57: 0 | AB57: 0
A58: 2025-01-15 | B58: 1FTFW5LD5RFC03772 | C58: 2024 | D58: FORD | E58: F-150 | F58: Truck | G58: Lease | H58: KRAUSE,JOSEPH FRANK | I58: Conventional | J58: JOSEPH | K58: KRAUSE | L58: 160 FRONT ST APT 413 | M58: BROOKLYN | N58: NY | O58: 11201 | P58: JOSEPHFKRAUSE@ICLOUD.COM | Q58: 267-261-6287 | R58: 267-261-6287 | S58: 267-261-6287 | T58: 0 | U58: 0 | V58: 0 | W58: 0 | X58: 0 | Y58: 0 | Z58: 0 | AA58: 0 | AB58: 0
A59: 2025-01-15 | B59: 1FD0W5HN4RED97963 | C59: 2024 | D59: FORD | E59: F-550 | F59: Truck | G59: Retail | H59: RAM-T CORPORATION | I59: Conventional | K59: RAM-T CORPORATION | L59: 1121 DOWNINGTOWN PIKE | M59: WEST CHESTER | N59: PA | O59: 19380-1641 | Q59: 610-972-8573 | T59: 0 | U59: 0 | V59: 0 | W59: 0 | X59: 0 | Y59: 0 | Z59: 0 | AA59: 0 | AB59: 0
A60: 2025-01-16 | B60: 1FDBF6Z88RKB46596 | C60: 2024 | D60: FORD | E60: TRANSIT | F60: Truck | G60: Retail | H60: FRED BEANS PARTS, INC. | I60: Fleet | K60: FRED BEANS PARTS, INC. | L60: 131 DOYLE ST | M60: DOYLESTOWN | N60: PA | O60: 18901-3701 | P60: rcostello@fredbeans.com | Q60: 215-348-0202 | R60: 215-348-0202 | T60: 0 | U60: 0 | V60: 0 | W60: 0 | X60: 0 | Y60: 0 | Z60: 0 | AA60: 0 | AB60: 0
A61: 2025-01-16 | B61: 1FDBF6Z80RKB46009 | C61: 2024 | D61: FORD | E61: TRANSIT | F61: Truck | G61: Retail | H61: FRED BEANS PARTS, INC. | I61: Fleet | K61: FRED BEANS PARTS, INC. | L61: 131 DOYLE ST | M61: DOYLESTOWN | N61: PA | O61: 18901-3701 | P61: rcostello@fredbeans.com | Q61: 215-348-0202 | R61: 215-348-0202 | T61: 0 | U61: 0 | V61: 0 | W61: 0 | X61: 0 | Y61: 0 | Z61: 0 | AA61: 0 | AB61: 0
A62: 2025-01-16 | B62: 1FDBF6Z86RKB46578 | C62: 2024 | D62: FORD | E62: TRANSIT | F62: Truck | G62: Retail | H62: FRED BEANS PARTS, INC. | I62: Fleet | K62: FRED BEANS PARTS, INC. | L62: 131 DOYLE ST | M62: DOYLESTOWN | N62: PA | O62: 18901-3701 | P62: rcostello@fredbeans.com | Q62: 215-348-0202 | R62: 215-348-0202 | T62: 0 | U62: 0 | V62: 0 | W62: 0 | X62: 0 | Y62: 0 | Z62: 0 | AA62: 0 | AB62: 0
A63: 2025-01-16 | B63: 1FDWF7DEXSDF09107 | C63: 2025 | D63: FORD MEDIUM TRUCKS | E63: F-750 | F63: Truck | G63: Retail | H63: FRED BEANS PARTS, INC. | I63: Fleet | K63: FRED BEANS PARTS, INC. | L63: 131 DOYLE ST | M63: DOYLESTOWN | N63: PA | O63: 18901-3701 | P63: rcostello@fredbeans.com | Q63: 215-348-0202 | R63: 215-348-0202 | T63: 0 | U63: 0 | V63: 0 | W63: 0 | X63: 0 | Y63: 0 | Z63: 0 | AA63: 0 | AB63: 0
A64: 2025-01-17 | B64: 1FD8X3FT5REF19929 | C64: 2024 | D64: FORD | E64: F-350 | F64: Truck | G64: Retail | H64: JAMES D MORRISSEY INC | I64: Fleet | K64: JAMES D MORRISSEY INC | L64: 9119 FRANKFORD AVE | M64: PHILADELPHIA | N64: PA | O64: 19114-2884 | P64: CA8186@AOL.COM | Q64: 215-539-3505 | R64: 215-333-8000 | S64: 215-651-5231 | T64: 0 | U64: 0 | V64: 0 | W64: 0 | X64: 0 | Y64: 0 | Z64: 0 | AA64: 0 | AB64: 0
A65: 2025-01-17 | B65: 3FMCR9D91RRF11807 | C65: 2024 | D65: FORD | E65: BRONCO SPORT | F65: Truck | G65: Retail | H65: STEWART,RAYMOND M | I65: Conventional | J65: RAYMOND | K65: STEWART | L65: 5966 COVERED BRIDGE RD | M65: PIPERSVILLE | N65: PA | O65: 18947 | P65: STEWARTK2@EMAIL.CHOP.EDU | Q65: 215-206-7734 | R65: 267-235-9753 | S65: 215-206-7734 | T65: 1500 | U65: 0 | V65: 500 | W65: 0 | X65: 0 | Y65: 0 | Z65: 0 | AA65: 0 | AB65: 0
A66: 2025-01-18 | B66: 1FMDE7BH9RLB48878 | C66: 2024 | D66: FORD | E66: BRONCO | F66: Truck | G66: Retail | H66: GILLMAN,ALEXIS PATRICIA | I66: Conventional | J66: ALEXIS | K66: GILLMAN | L66: 112 ARBOR RD | M66: CHURCHVILLE | N66: PA | O66: 18966-1082 | P66: ALEXISGILLMAN@GMAIL.COM | Q66: 267-832-8106 | R66: 267-832-8106 | T66: 652 | U66: 0 | V66: 0 | W66: 0 | X66: 0 | Y66: 0 | Z66: 0 | AA66: 0 | AB66: 0
A67: 2025-01-18 | B67: 3FTTW8H37SRA14120 | C67: 2025 | D67: FORD | E67: MAVERICK | F67: Truck | G67: Retail | H67: NEAGLEY,DANIEL | I67: Conventional | J67: DANIEL | K67: NEAGLEY | L67: 326 KATIE LN | M67: PERKASIE | N67: PA | O67: 18944-3205 | P67: NEAGLEYDE@GMAIL.COM | Q67: 267-443-0137 | R67: 267-443-0137 | S67: 267-443-0137 | T67: 0 | U67: 0 | V67: 0 | W67: 0 | X67: 0 | Y67: 0 | Z67: 0 | AA67: 0 | AB67: 0
A68: 2025-01-18 | B68: 1FMJK1M81REA80554 | C68: 2024 | D68: FORD | E68: EXPEDITION MAX | F68: Truck | G68: Retail | H68: ROMANO,SUZANNE RANDOLPH | I68: Conventional | J68: SUZANNE | K68: ROMANO | L68: 3 DUKE LN | M68: AMBLER | N68: PA | O68: 19002 | P68: SUZ_RANDOLPH@YAHOO.COM | Q68: 215-704-1178 | R68: 215-704-1178 | S68: 215-704-1178 | T68: 1315 | U68: 0 | V68: 0 | W68: 0 | X68: 0 | Y68: 431 | Z68: 0 | AA68: 0 | AB68: 0
A69: 2025-01-18 | B69: 3FTTW8S9XRRB73222 | C69: 2024 | D69: FORD | E69: MAVERICK | F69: Truck | G69: Retail | H69: LUNEAU,KATHY | I69: Conventional | J69: KATHY | K69: LUNEAU | L69: 1221 EAGLE RD | M69: NEWTOWN | N69: PA | O69: 18940 | P69: JOHN@LUNEAULAW.NET | Q69: 267-374-8318 | R69: 267-566-3162 | S69: 267-374-8318 | T69: 2500 | U69: 0 | V69: 600 | W69: 0 | X69: 0 | Y69: 653 | Z69: 0 | AA69: 0 | AB69: 0
A70: 2025-01-18 | B70: 3FMTK3SU4RMA48714 | C70: 2024 | D70: FORD | E70: MUSTME | F70: Truck | G70: Lease | H70: DRAGOS,KENNETH C | I70: Conventional | J70: KENNETH | K70: DRAGOS | L70: 4370 WENTWORTH CT | M70: NEW HOPE | N70: PA | O70: 18938 | P70: KEND0319@GMAIL.COM | Q70: 215-669-6941 | R70: 215-669-6941 | S70: 215-669-6941 | T70: 0 | U70: 0 | V70: 65 | W70: 0 | X70: 0 | Y70: 0 | Z70: 0 | AA70: 0 | AB70: 0
A71: 2025-01-18 | B71: 1FTVW3LK1RWG20059 | C71: 2024 | D71: FORD | E71: F-150 | F71: Truck | G71: Lease | H71: SNYDER,CHRISTOPHER CHARLES | I71: Conventional | J71: CHRISTOPHER | K71: SNYDER | L71: 728 PLEASANT WAY | M71: UNION DALE | N71: PA | O71: 18470-9796 | Q71: 610-299-2470 | R71: 610-299-2470 | S71: 610-299-2470 | T71: 0 | U71: 0 | V71: 0 | W71: 0 | X71: 0 | Y71: 677 | Z71: 0 | AA71: 0 | AB71: 0
A72: 2025-01-20 | B72: 3FMTK3SU0RMA48855 | C72: 2024 | D72: FORD | E72: MUSTME | F72: Truck | G72: Lease | H72: KIMBALL,WILLIAM E | I72: Conventional | J72: WILLIAM | K72: KIMBALL | L72: 1142 WEBB DR | M72: PERKASIE | N72: PA | O72: 18944-4443 | P72: WEKIMBALL@GMAIL.COM | Q72: 203-206-5604 | R72: 203-206-5604 | S72: 203-206-5604 | T72: 0 | U72: 0 | V72: 0 | W72: 0 | X72: 0 | Y72: 0 | Z72: 0 | AA72: 0 | AB72: 0
A73: 2025-01-20 | B73: 1FTFW1RG2SFA04825 | C73: 2025 | D73: FORD | E73: F-150 | F73: Truck | G73: Retail | H73: HARTMAN LANDSCAPING, LLC | I73: Conventional | K73: HARTMAN LANDSCAPING, LLC | L73: 61 PULASKI RD | M73: WHITEHOUSE STATION | N73: NJ | O73: 08889-3523 | P73: HARTMANLANDSCAPINGLLC@GMAIL.COM | Q73: 908-256-0759 | R73: 908-256-0759 | S73: 908-256-0759 | T73: 1000 | U73: 0 | V73: 0 | W73: 0 | X73: 0 | Y73: 0 | Z73: 0 | AA73: 0 | AB73: 0
A74: 2025-01-20 | B74: 1FT8W2BN2REE07355 | C74: 2024 | D74: FORD | E74: F-250 | F74: Truck | G74: Retail | H74: LIND,CODY ROBERT | I74: Conventional | J74: CODY | K74: LIND | L74: 507 POLO RUN | M74: WEST CHESTER | N74: PA | O74: 19380-7100 | P74: CODYRLIND1@GMAIL.COM | Q74: 484-678-5089 | R74: 484-678-5089 | S74: 484-678-5089 | T74: 1900 | U74: 0 | V74: 0 | W74: 0 | X74: 0 | Y74: 559 | Z74: 0 | AA74: 0 | AB74: 0
A75: 2025-01-20 | B75: 1FT6W5L71RWG24768 | C75: 2024 | D75: FORD | E75: F-150 | F75: Truck | G75: Retail | H75: RHODES,KELVIN LEE | I75: Conventional | J75: KELVIN | K75: RHODES | L75: 824 3RD AVE | M75: BRISTOL | N75: PA | O75: 19007 | P75: ELITO86@GMAIL.COM | Q75: 215-200-7097 | R75: 215-200-7097 | S75: 215-200-7097 | T75: 3000 | U75: 0 | V75: 0 | W75: 0 | X75: 0 | Y75: 431 | Z75: 0 | AA75: 0 | AB75: 0
A76: 2025-01-21 | B76: 1FT8W3BM6SEC09848 | C76: 2025 | D76: FORD | E76: F-350 | F76: Truck | G76: Retail | H76: BLUEWATER LOGISTICS LLC | I76: Conventional | K76: BLUEWATER LOGISTICS LLC | L76: 281 CENTENNIAL AVE STE 1 | M76: PISCATAWAY | N76: NJ | O76: 08854-3949 | Q76: 845-866-3127 | T76: 500 | U76: 0 | V76: 0 | W76: 0 | X76: 0 | Y76: 0 | Z76: 0 | AA76: 0 | AB76: 0
A77: 2025-01-21 | B77: 1FD0X4HN1REF24143 | C77: 2024 | D77: FORD | E77: F-450 | F77: Truck | G77: Retail | H77: REGALBUTO LANDSCAPING LLC | I77: Conventional | K77: REGALBUTO LANDSCAPING LLC | L77: 249 ROSENHAYN AVE | M77: BRIDGETON | N77: NJ | O77: 08302-6116 | P77: RENORLANDSCAPING@AOL.COM | Q77: 856-466-1356 | T77: 500 | U77: 0 | V77: 0 | W77: 0 | X77: 0 | Y77: 0 | Z77: 0 | AA77: 0 | AB77: 0
A78: 2025-01-21 | B78: 3FMCR9D91RRF48713 | C78: 2024 | D78: FORD | E78: BRONCO SPORT | F78: Truck | G78: Lease | H78: TUDOR,ESME VICTORIA | I78: Conventional | J78: ESME | K78: TUDOR | L78: 473 GEIGEL HILL RD | M78: OTTSVILLE | N78: PA | O78: 18942 | P78: ESMETUDOR22@GMAIL.COM | Q78: 610-847-8837 | R78: 551-427-0265 | S78: 551-427-0265 | T78: 0 | U78: 0 | V78: 0 | W78: 0 | X78: 0 | Y78: 0 | Z78: 0 | AA78: 0 | AB78: 0
A79: 2025-01-22 | B79: 1FDRF3FN6PEC59028 | C79: 2023 | D79: FORD | E79: F-350 | F79: Truck | G79: Retail | H79: BARRICELLI CONSTRUCTION INC | I79: Conventional | K79: BARRICELLI CONSTRUCTION INC | L79: 110 TINARI DR | M79: RICHBORO | N79: PA | O79: 18954-2057 | Q79: 267-784-8560 | S79: 215-669-4579 | T79: 650 | U79: 0 | V79: 0 | W79: 0 | X79: 0 | Y79: 0 | Z79: 0 | AA79: 0 | AB79: 0
A80: 2025-01-22 | B80: 1FTBR1C87RKB73201 | C80: 2024 | D80: FORD | E80: TRANSIT | F80: Truck | G80: Retail | H80: EMPIRE REFRIGERATION | I80: Conventional | K80: EMPIRE REFRIGERATION | L80: 64 OCEAN AVE | M80: LYNBROOK | N80: NY | O80: 11563 | P80: JOE@EMPIREREFRIGERATION.COM | Q80: 516-837-3500 | T80: 0 | U80: 0 | V80: 0 | W80: 0 | X80: 0 | Y80: 0 | Z80: 0 | AA80: 0 | AB80: 0
A81: 2025-01-23 | B81: 1FMUK8KH1SGA61361 | C81: 2025 | D81: FORD | E81: EXPLORER | F81: Truck | G81: Retail | H81: FOLEY JR,EUGENE EDWARD | I81: Conventional | J81: EUGENE | K81: FOLEY | L81: 81 FLORENCE DR | M81: RICHBORO | N81: PA | O81: 18954-1444 | P81: GENEFOLEY300@GMAIL.COM | Q81: 215-605-8032 | S81: 215-605-8032 | T81: 0 | U81: 0 | V81: 0 | W81: 0 | X81: 0 | Y81: 0 | Z81: 0 | AA81: 0 | AB81: 0
A82: 2025-01-23 | B82: 1FTFW1P86RKE65409 | C82: 2024 | D82: FORD | E82: F-150 | F82: Truck | G82: Retail | H82: AXON ENTERPRISE, INC. | I82: Fleet | K82: AXON ENTERPRISE, INC. | L82: 17800 N 85TH ST | M82: SCOTTSDALE | N82: AZ | O82: 85255-6311 | Q82: 205-806-0123 | T82: 0 | U82: 0 | V82: 0 | W82: 0 | X82: 0 | Y82: 0 | Z82: 0 | AA82: 0 | AB82: 0
A83: 2025-01-23 | B83: 1FTBF2BA1REF91657 | C83: 2024 | D83: FORD | E83: F-250 | F83: Truck | G83: Retail | H83: NACEVILLE MATERIALS JOINT VENTURE | I83: Fleet | K83: NACEVILLE MATERIALS JOINT VENTURE | L83: 350 S MAIN ST STE 207 | M83: DOYLESTOWN | N83: PA | O83: 18901 | P83: BMILLER@MILLERSONPAVING.COM | Q83: 267-880-2422 | R83: 267-880-2422 | S83: 215-416-4055 | T83: 0 | U83: 0 | V83: 0 | W83: 0 | X83: 0 | Y83: 0 | Z83: 0 | AA83: 0 | AB83: 0
A84: 2025-01-23 | B84: 1FTFW3LD7RFA08874 | C84: 2024 | D84: FORD | E84: F-150 | F84: Truck | G84: Retail | H84: THE EDGEWOOD COMPANY, INC. | I84: Conventional | K84: THE EDGEWOOD COMPANY, INC. | L84: 2350 YELLOW SPRINGS RD | M84: MALVERN | N84: PA | O84: 19355-9758 | P84: WJF@EDGEWOODCO.COM | Q84: 484-866-3401 | S84: 484-866-3401 | T84: 0 | U84: 0 | V84: 0 | W84: 0 | X84: 0 | Y84: 0 | Z84: 0 | AA84: 0 | AB84: 0
A85: 2025-01-23 | B85: 1FMDE7BH1RLB50043 | C85: 2024 | D85: FORD | E85: BRONCO | F85: Truck | G85: Retail | H85: DONAHUE,RYAN CHRISTOPHER | I85: Conventional | J85: RYAN | K85: DONAHUE | L85: 7101 APPELMAN RD | M85: CHESTERFIELD | N85: VA | O85: 23832-2201 | P85: RDONAHUE61@GMAIL.COM | Q85: 267-897-0181 | R85: 267-897-0181 | S85: 267-897-0181 | T85: 0 | U85: 0 | V85: 0 | W85: 0 | X85: 0 | Y85: 0 | Z85: 0 | AA85: 0 | AB85: 0
A86: 2025-01-23 | B86: 1FTBR3UG2RKA85853 | C86: 2024 | D86: FORD | E86: TRANSIT | F86: Truck | G86: Retail | H86: RASTELLI BROTHERS INC | I86: Conventional | K86: RASTELLI BROTHERS INC | L86: 300 HERON DR | M86: SWEDESBORO | N86: NJ | O86: 08085-1707 | P86: TPERRY@RASTELLIS.COM | Q86: 856-217-7577 | R86: 312-805-0021 | S86: 267-816-5647 | T86: 0 | U86: 0 | V86: 0 | W86: 0 | X86: 0 | Y86: 0 | Z86: 0 | AA86: 0 | AB86: 0
A87: 2025-01-23 | B87: 1FMWK8GC3SGA92150 | C87: 2025 | D87: FORD | E87: EXPLORER | F87: Truck | G87: Retail | H87: MARTYNIUK,ULADZIMIR | I87: Conventional | J87: ULADZIMIR | K87: MARTYNIUK | L87: 675 E STREET RD APT 1619 | M87: WARMINSTER | N87: PA | O87: 18974-3516 | P87: VLADZIMIR.MARTYNUK@OUTLOOK.COM | Q87: 267-894-6435 | R87: 267-894-6435 | S87: 267-894-6435 | T87: 0 | U87: 0 | V87: 275 | W87: 0 | X87: 0 | Y87: 0 | Z87: 0 | AA87: 0 | AB87: 0
A88: 2025-01-23 | B88: 1FMEE2BP0RLB03052 | C88: 2024 | D88: FORD | E88: BRONCO | F88: Truck | G88: Retail | H88: KUEHNE,RICHARD | I88: Conventional | J88: RICHARD | K88: KUEHNE | L88: 285 CHAPMAN RD | M88: DOYLESTOWN | N88: PA | O88: 18901 | P88: KUEHNE11@ICLOUD.COM | Q88: 215-460-0124 | R88: 215-460-0124 | S88: 215-622-5284 | T88: 100 | U88: 0 | V88: 0 | W88: 0 | X88: 0 | Y88: 0 | Z88: 0 | AA88: 0 | AB88: 0
A89: 2025-01-24 | B89: 1FTMF1KP7SKD12646 | C89: 2025 | D89: F-150 | E89: FORD | F89: Truck | G89: Retail | H89: PRINCETON UNIVERSITY | I89: Fleet | K89: PRINCETON UNIVERSITY | L89: PO BOX 33 | M89: PRINCETON | N89: NJ | O89: 08543-0033 | P89: MH25@PRINCETON.EDU | Q89: 609-947-5852 | R89: 609-258-5033 | S89: 609-258-5033 | T89: 0 | U89: 0 | V89: 0 | W89: 0 | X89: 0 | Y89: 0 | Z89: 0 | AA89: 0 | AB89: 0
A90: 2025-01-24 | B90: 1FTFW6L83SFA17422 | C90: 2025 | D90: FORD | E90: F-150 | F90: Truck | G90: Retail | H90: VERCOE,SCOTT ERICSON | I90: Conventional | J90: SCOTT | K90: VERCOE | L90: 3 WINDING WAY | M90: MALVERN | N90: PA | O90: 19355-1718 | P90: GROUTGUY66@AOL.COM | Q90: 610-659-3344 | S90: 610-659-3344 | T90: 0 | U90: 0 | V90: 0 | W90: 0 | X90: 0 | Y90: 748 | Z90: 0 | AA90: 0 | AB90: 0
A91: 2025-01-24 | B91: 3FTTW8H32SRA00352 | C91: 2025 | D91: FORD | E91: MAVERICK | F91: Truck | G91: Retail | H91: THOMASVILLE RESTORATION LLC | I91: Conventional | K91: THOMASVILLE RESTORATION LLC | L91: 1611 KNECHT AVE | M91: BALTIMORE | N91: MD | O91: 21227-1509 | P91: TOMN@TVR247.COM | Q91: 443-623-4545 | S91: 443-623-4545 | T91: 0 | U91: 0 | V91: 0 | W91: 0 | X91: 0 | Y91: 0 | Z91: 0 | AA91: 0 | AB91: 0
A92: 2025-01-24 | B92: 1FTFW7LD1SFA04123 | C92: 2025 | D92: FORD | E92: F-150 HYBRID | F92: Truck | G92: Retail | H92: AQUA-LINK, INC. | I92: Conventional | K92: AQUA-LINK, INC. | L92: 1519 BROAD ST | M92: PERKASIE | N92: PA | O92: 18944-3455 | P92: MMINERS@AQUALINKINC.COM | Q92: 215-852-5873 | R92: 215-230-9325 | S92: 215-589-5595 | T92: 0 | U92: 0 | V92: 0 | W92: 0 | X92: 0 | Y92: 0 | Z92: 0 | AA92: 0 | AB92: 0
A93: 2025-01-24 | B93: 1FDRF3FN6PEC59028 | C93: 2023 | D93: FORD | E93: F-350 | F93: Truck | G93: Retail | H93: BARRICELLI CONSTRUCTION INC | I93: Conventional | K93: BARRICELLI CONSTRUCTION INC | L93: 110 TINARI DR | M93: RICHBORO | N93: PA | O93: 18954-2057 | Q93: 267-784-8560 | S93: 215-669-4579 | T93: 0 | U93: 0 | V93: 0 | W93: 0 | X93: 0 | Y93: 0 | Z93: 0 | AA93: 0 | AB93: 0
A94: 2025-01-24 | B94: 1FTFW3LD1RFB43168 | C94: 2024 | D94: FORD | E94: F-150 HYBRID | F94: Truck | G94: Retail | H94: EBERT,ROBERT | I94: Conventional | J94: ROBERT | K94: EBERT | L94: 114 SADDLE DR | M94: FURLONG | N94: PA | O94: 18925 | P94: RJEBERT@VERIZON.NET | Q94: 215-340-9666 | R94: 215-340-9666 | S94: 215-340-9666 | T94: 0 | U94: 0 | V94: 0 | W94: 0 | X94: 0 | Y94: 0 | Z94: 0 | AA94: 0 | AB94: 0
A95: 2025-01-24 | B95: 1FMDE7BHXRLB50364 | C95: 2024 | D95: FORD | E95: BRONCO | F95: Truck | G95: Retail | H95: YIZZI,ROBERT ALAN | I95: Conventional | J95: ROBERT | K95: YIZZI | L95: 36 ALEXANDERS CT | M95: NEWTOWN | N95: PA | O95: 18940-3640 | P95: RYIZZI@COMCAST.NET | Q95: 215-968-2665 | R95: 267-261-4886 | S95: 267-261-4886 | T95: 0 | U95: 0 | V95: 0 | W95: 0 | X95: 0 | Y95: 749 | Z95: 0 | AA95: 0 | AB95: 0
A96: 2025-01-24 | B96: 1FTBR1X81RKB73074 | C96: 2024 | D96: FORD | E96: TRANSIT | F96: Truck | G96: Retail | H96: STROUDSBURG AREA SCHOOL DISTRICT | I96: Fleet | K96: STROUDSBURG AREA SCHOOL DISTRICT | L96: 123 LINDEN ST | M96: STROUDSBURG | N96: PA | O96: 18360-1399 | Q96: 123-456-7890 | T96: 0 | U96: 0 | V96: 0 | W96: 0 | X96: 0 | Y96: 0 | Z96: 0 | AA96: 0 | AB96: 0
A97: 2025-01-25 | B97: 1FMCU0MN6RUB26789 | C97: 2024 | D97: FORD | E97: ESCAPE | F97: Truck | G97: Lease | H97: TORO-TROCHE,MARIBEL | I97: Conventional | J97: MARIBEL | K97: TORO-TROCHE | L97: 4820 STUMP RD | M97: PIPERSVILLE | N97: PA | O97: 18947-1802 | P97: MTTKIDSMD@GMAIL.COM | Q97: 267-885-7145 | R97: 215-324-0600 | S97: 267-885-7145 | T97: 0 | U97: 0 | V97: 0 | W97: 0 | X97: 0 | Y97: 190 | Z97: 0 | AA97: 0 | AB97: 0
A98: 2025-01-25 | B98: 1FMDE8BH2RLB48954 | C98: 2024 | D98: FORD | E98: BRONCO | F98: Truck | G98: Retail | H98: SPRADLIN,MEGAN MARIE | I98: Conventional | J98: MEGAN | K98: SPRADLIN | L98: 5181 ROSEWOOD DR | M98: DOYLESTOWN | N98: PA | O98: 18902 | P98: MCNULTYMEGAN0@GMAIL.COM | Q98: 386-898-3119 | R98: 386-898-3119 | S98: 267-564-0139 | T98: 0 | U98: 0 | V98: 0 | W98: 0 | X98: 0 | Y98: 748 | Z98: 0 | AA98: 0 | AB98: 0
A99: 2025-01-25 | B99: 1FMDE8BH4RLB50463 | C99: 2024 | D99: FORD | E99: BRONCO | F99: Truck | G99: Retail | H99: MANN,CAROLYN MARIA | I99: Conventional | J99: CAROLYN | K99: MANN | L99: 206 NORTHPARK DR | M99: LEVITTOWN | N99: PA | O99: 19054-3330 | P99: CMANN0426@COMCAST.NET | Q99: 267-673-9493 | S99: 267-673-9493 | T99: 2500 | U99: 0 | V99: 220 | W99: 0 | X99: 0 | Y99: 431 | Z99: 0 | AA99: 0 | AB99: 0
A100: 2025-01-25 | B100: 1FTFW2L50RKE95457 | C100: 2024 | D100: FORD | E100: F-150 | F100: Truck | G100: Lease | H100: SHEETS,JOSHUA LEE | I100: Conventional | J100: JOSHUA | K100: SHEETS | L100: 1196 QUAIL RD | M100: KUNKLETOWN | N100: PA | O100: 18058 | P100: JOSHSHEETS01@VERIZON.NET | Q100: 267-354-1106 | R100: 610-960-9375 | S100: 610-960-9375 | T100: 0 | U100: 0 | V100: 0 | W100: 0 | X100: 0 | Y100: 0 | Z100: 0 | AA100: 0 | AB100: 0
...

Sheet Sheet1
A3: DOYLESTOWN | B3: 852
A4: PHILADELPHIA | B4: 341 | F4: ALLENTOWN
A5: PERKASIE | B5: 244 | F5: AMBLER
A6: CHALFONT | B6: 224 | F6: BENSALEM
A7: WARMINSTER | B7: 211 | F7: BLUE BELL
A8: WARRINGTON | B8: 206 | F8: BRISTOL
A9: PIPERSVILLE | B9: 174 | F9: CHALFONT
A10: NEW HOPE | B10: 157 | F10: DOYLESTOWN
A11: NEWTOWN | B11: 149 | F11: EASTON
A12: LANSDALE | B12: 125 | F12: FURLONG
A13: QUAKERTOWN | B13: 124 | F13: HATBORO
A14: FURLONG | B14: 107 | F14: HATFIELD
A15: JAMISON | B15: 97 | F15: HOLLAND
... A36: RICHBORO | B36: 51 | F36: WARRINGTON
F37: YARDLEY
A38: WEST CHESTER | B38: 48
A39: CHERRY HILL | B39: 47
A40: BETHLEHEM | B40: 46
A41: HARLEYSVILLE | B41: 45
A42: WORCESTER | B42: 44
A43: SPARKS | B43: 43
A44: OTTSVILLE | B44: 38
A45: IVYLAND | B45: 38
A46: ST. LOUIS | B46: 38
A47: TELFORD | B47: 37
A48: WILLOW GROVE | B48: 36
A49: CONSHOHOCKEN | B49: 35
... A1126: LEDERACH | B1126: 1

Sheet Call List
B2: NAME | C2: COUNT | D2: Type | E2: Street | F2: City | G2: State | H2: Zip Code | I2: Email | J2: Cell Phone
B3: PRINCETON UNIVERSITY | C3: 58 | D3: =VLOOKUP($B3,'F&I Log'!$H$3:$I$8977,2,FALSE) -> Fleet | E3: =(VLOOKUP($B3,'F&I Log'!$H$3:$S$8977,5,FALSE)) -> PO BOX 33 | F3: =IFERROR(VLOOKUP($B3,'F&I Log'!$H$3:$S$8977,6,FALSE),"--") -> PRINCETON | G3: =IFERROR(VLOOKUP($B3,'F&I Log'!$H$3:$S$8977,7,FALSE),"--") -> NJ | H3: =IFERROR(VLOOKUP($B3,'F&I Log'!$H$3:$S$8977,8,FALSE),"--") -> 08543-0033 | I3: =IFERROR(VLOOKUP($B3,'F&I Log'!$H$3:$S$8977,9,FALSE),"--") -> MH25@PRINCETON.EDU | J3: =IFERROR(VLOOKUP($B3,'F&I Log'!$H$3:$S$8977,10,FALSE),"--") -> 609-947-5852
B4: JAMES D MORRISSEY INC | C4: 40 | D4: =VLOOKUP($B4,'F&I Log'!$H$3:$I$8977,2,FALSE) -> Fleet | E4: =(VLOOKUP($B4,'F&I Log'!$H$3:$S$8977,5,FALSE)) -> 9119 FRANKFORD AVE | F4: =IFERROR(VLOOKUP($B4,'F&I Log'!$H$3:$S$8977,6,FALSE),"--") -> PHILADELPHIA | G4: =IFERROR(VLOOKUP($B4,'F&I Log'!$H$3:$S$8977,7,FALSE),"--") -> PA | H4: =IFERROR(VLOOKUP($B4,'F&I Log'!$H$3:$S$8977,8,FALSE),"--") -> 19114-2884 | I4: =IFERROR(VLOOKUP($B4,'F&I Log'!$H$3:$S$8977,9,FALSE),"--") -> CA8186@AOL.COM | J4: =IFERROR(VLOOKUP($B4,'F&I Log'!$H$3:$S$8977,10,FALSE),"--") -> 215-539-3505
B5: GLESBY MARKS LTD | C5: 35 | D5: =VLOOKUP($B5,'F&I Log'!$H$3:$I$8977,2,FALSE) -> Fleet | E5: =(VLOOKUP($B5,'F&I Log'!$H$3:$S$8977,5,FALSE)) -> PO BOX 4875 | F5: =IFERROR(VLOOKUP($B5,'F&I Log'!$H$3:$S$8977,6,FALSE),"--") -> HOUSTON | G5: =IFERROR(VLOOKUP($B5,'F&I Log'!$H$3:$S$8977,7,FALSE),"--") -> TX | H5: =IFERROR(VLOOKUP($B5,'F&I Log'!$H$3:$S$8977,8,FALSE),"--") -> 77210 | I5: =IFERROR(VLOOKUP($B5,'F&I Log'!$H$3:$S$8977,9,FALSE),"--") -> KCASEY@4DONNELLYS.COM | J5: =IFERROR(VLOOKUP($B5,'F&I Log'!$H$3:$S$8977,10,FALSE),"--") -> 713-366-8223
B6: R & S HARDSCAPING, LLC | C6: 28 | D6: =VLOOKUP($B6,'F&I Log'!$H$3:$I$8977,2,FALSE) -> Conventional | E6: =(VLOOKUP($B6,'F&I Log'!$H$3:$S$8977,5,FALSE)) -> 765 SANATOGA ROAD | F6: =IFERROR(VLOOKUP($B6,'F&I Log'!$H$3:$S$8977,6,FALSE),"--") -> POTTSTOWN | G6: =IFERROR(VLOOKUP($B6,'F&I Log'!$H$3:$S$8977,7,FALSE),"--") -> PA | H6: =IFERROR(VLOOKUP($B6,'F&I Log'!$H$3:$S$8977,8,FALSE),"--") -> 19465 | I6: =IFERROR(VLOOKUP($B6,'F&I Log'!$H$3:$S$8977,9,FALSE),"--") | J6: =IFERROR(VLOOKUP($B6,'F&I Log'!$H$3:$S$8977,10,FALSE),"--") -> 484-624-2810
B7: DONLEN TRUST | C7: 21 | D7: =VLOOKUP($B7,'F&I Log'!$H$3:$I$8977,2,FALSE) -> Fleet | E7: =(VLOOKUP($B7,'F&I Log'!$H$3:$S$8977,5,FALSE)) -> 666 GARLAND PLACE | F7: =IFERROR(VLOOKUP($B7,'F&I Log'!$H$3:$S$8977,6,FALSE),"--") -> DES PLAINES | G7: =IFERROR(VLOOKUP($B7,'F&I Log'!$H$3:$S$8977,7,FALSE),"--") -> IL | H7: =IFERROR(VLOOKUP($B7,'F&I Log'!$H$3:$S$8977,8,FALSE),"--") -> 60016 | I7: =IFERROR(VLOOKUP($B7,'F&I Log'!$H$3:$S$8977,9,FALSE),"--") -> BTAYLOR@DONLEN.COM | J7: =IFERROR(VLOOKUP($B7,'F&I Log'!$H$3:$S$8977,10,FALSE),"--") -> 847-412-4961
B8: THE SUPREME COURT OF THE UNITED STATES | C8: 21 | D8: =VLOOKUP($B8,'F&I Log'!$H$3:$I$8977,2,FALSE) -> Fleet | E8: =(VLOOKUP($B8,'F&I Log'!$H$3:$S$8977,5,FALSE)) -> 1 1ST ST NE | F8: =IFERROR(VLOOKUP($B8,'F&I Log'!$H$3:$S$8977,6,FALSE),"--") -> WASHINGTON | G8: =IFERROR(VLOOKUP($B8,'F&I Log'!$H$3:$S$8977,7,FALSE),"--") -> DC | H8: =IFERROR(VLOOKUP($B8,'F&I Log'!$H$3:$S$8977,8,FALSE),"--") -> 20543-0002 | I8: =IFERROR(VLOOKUP($B8,'F&I Log'!$H$3:$S$8977,9,FALSE),"--") | J8: =IFERROR(VLOOKUP($B8,'F&I Log'!$H$3:$S$8977,10,FALSE),"--")
B9: FIFTH THIRD BANK NATIONAL ASSOC | C9: 20 | D9: =VLOOKUP($B9,'F&I Log'!$H$3:$I$8977,2,FALSE) -> Fleet | E9: =(VLOOKUP($B9,'F&I Log'!$H$3:$S$8977,5,FALSE)) -> 38 FOUNTAIN SQUARE PLZ | F9: =IFERROR(VLOOKUP($B9,'F&I Log'!$H$3:$S$8977,6,FALSE),"--") -> CINCINNATI | G9: =IFERROR(VLOOKUP($B9,'F&I Log'!$H$3:$S$8977,7,FALSE),"--") -> OH | H9: =IFERROR(VLOOKUP($B9,'F&I Log'!$H$3:$S$8977,8,FALSE),"--") -> 45202-3102 | I9: =IFERROR(VLOOKUP($B9,'F&I Log'!$H$3:$S$8977,9,FALSE),"--") -> SEAN.HOLDEN@53.COM | J9: =IFERROR(VLOOKUP($B9,'F&I Log'!$H$3:$S$8977,10,FALSE),"--") -> 443-798-6520
B10: PRINCIPLE ENTERPRISES, LLC | C10: 17 | D10: =VLOOKUP($B10,'F&I Log'!$H$3:$I$8977,2,FALSE) -> Conventional | E10: =(VLOOKUP($B10,'F&I Log'!$H$3:$S$8977,5,FALSE)) -> PO BOX 177 | F10: =IFERROR(VLOOKUP($B10,'F&I Log'!$H$3:$S$8977,6,FALSE),"--") -> CANTON | G10: =IFERROR(VLOOKUP($B10,'F&I Log'!$H$3:$S$8977,7,FALSE),"--") -> PA | H10: =IFERROR(VLOOKUP($B10,'F&I Log'!$H$3:$S$8977,8,FALSE),"--") -> 17724-0177 | I10: =IFERROR(VLOOKUP($B10,'F&I Log'!$H$3:$S$8977,9,FALSE),"--") -> mpapalia@principleenterprises.com | J10: =IFERROR(VLOOKUP($B10,'F&I Log'!$H$3:$S$8977,10,FALSE),"--") -> 570-250-5101
B11: BBC REAL ESTATE HOLDING CO LLC | C11: 16 | D11: =VLOOKUP($B11,'F&I Log'!$H$3:$I$8977,2,FALSE) -> Fleet | E11: =(VLOOKUP($B11,'F&I Log'!$H$3:$S$8977,5,FALSE)) -> 2701 BARTRAM RD | F11: =IFERROR(VLOOKUP($B11,'F&I Log'!$H$3:$S$8977,6,FALSE),"--") -> BRISTOL | G11: =IFERROR(VLOOKUP($B11,'F&I Log'!$H$3:$S$8977,7,FALSE),"--") -> PA | H11: =IFERROR(VLOOKUP($B11,'F&I Log'!$H$3:$S$8977,8,FALSE),"--") -> 19007 | I11: =IFERROR(VLOOKUP($B11,'F&I Log'!$H$3:$S$8977,9,FALSE),"--") | J11: =IFERROR(VLOOKUP($B11,'F&I Log'!$H$3:$S$8977,10,FALSE),"--") -> 215-788-2700
B12: D L PETERSON TRUST | C12: 15 | D12: =VLOOKUP($B12,'F&I Log'!$H$3:$I$8977,2,FALSE) -> Fleet | E12: =(VLOOKUP($B12,'F&I Log'!$H$3:$S$8977,5,FALSE)) -> 940 RIDGEBROOK RD | F12: =IFERROR(VLOOKUP($B12,'F&I Log'!$H$3:$S$8977,6,FALSE),"--") -> SPARKS | G12: =IFERROR(VLOOKUP($B12,'F&I Log'!$H$3:$S$8977,7,FALSE),"--") -> MD | H12: =IFERROR(VLOOKUP($B12,'F&I Log'!$H$3:$S$8977,8,FALSE),"--") -> 21152 | I12: =IFERROR(VLOOKUP($B12,'F&I Log'!$H$3:$S$8977,9,FALSE),"--") | J12: =IFERROR(VLOOKUP($B12,'F&I Log'!$H$3:$S$8977,10,FALSE),"--") -> 410-771-2203
B13: ENTERPRISE FM TRUST LSR | C13: 14 | D13: =VLOOKUP($B13,'F&I Log'!$H$3:$I$8977,2,FALSE) -> Fleet | E13: =(VLOOKUP($B13,'F&I Log'!$H$3:$S$8977,5,FALSE)) -> 2281 BALL DRIVE | F13: =IFERROR(VLOOKUP($B13,'F&I Log'!$H$3:$S$8977,6,FALSE),"--") -> ST LOUIS | G13: =IFERROR(VLOOKUP($B13,'F&I Log'!$H$3:$S$8977,7,FALSE),"--") -> MO | H13: =IFERROR(VLOOKUP($B13,'F&I Log'!$H$3:$S$8977,8,FALSE),"--") -> 63146 | I13: =IFERROR(VLOOKUP($B13,'F&I Log'!$H$3:$S$8977,9,FALSE),"--") | J13: =IFERROR(VLOOKUP($B13,'F&I Log'!$H$3:$S$8977,10,FALSE),"--")
B14: BILL WISE'S EXCAVATING INC | C14: 12 | D14: =VLOOKUP($B14,'F&I Log'!$H$3:$I$8977,2,FALSE) -> Conventional | E14: =(VLOOKUP($B14,'F&I Log'!$H$3:$S$8977,5,FALSE)) -> 944 JOLLYTOWN RD | F14: =IFERROR(VLOOKUP($B14,'F&I Log'!$H$3:$S$8977,6,FALSE),"--") -> NEW FREEPORT | G14: =IFERROR(VLOOKUP($B14,'F&I Log'!$H$3:$S$8977,7,FALSE),"--") -> PA | H14: =IFERROR(VLOOKUP($B14,'F&I Log'!$H$3:$S$8977,8,FALSE),"--") -> 15352-1574 | I14: =IFERROR(VLOOKUP($B14,'F&I Log'!$H$3:$S$8977,9,FALSE),"--") | J14: =IFERROR(VLOOKUP($B14,'F&I Log'!$H$3:$S$8977,10,FALSE),"--") -> 724-451-8175
... B6246: MERRITT,KENNETH CHARLES | C6246: 1 | D6246: =VLOOKUP($B6246,'F&I Log'!$H$3:$I$8977,2,FALSE) -> Conventional | E6246: =(VLOOKUP($B6246,'F&I Log'!$H$3:$S$8977,5,FALSE)) -> 83 PATRIOT DR | F6246: =IFERROR(VLOOKUP($B6246,'F&I Log'!$H$3:$S$8977,6,FALSE),"--") -> CHALFONT | G6246: =IFERROR(VLOOKUP($B6246,'F&I Log'!$H$3:$S$8977,7,FALSE),"--") -> PA | H6246: =IFERROR(VLOOKUP($B6246,'F&I Log'!$H$3:$S$8977,8,FALSE),"--") -> 18914-2953 | I6246: =IFERROR(VLOOKUP($B6246,'F&I Log'!$H$3:$S$8977,9,FALSE),"--") -> KMERRITT6958@GMAIL.COM | J6246: =IFERROR(VLOOKUP($B6246,'F&I Log'!$H$3:$S$8977,10,FALSE),"--") -> 215-997-7517

Sheet Sheet2
A1: VIN | B1: Year | C1: Make | D1: Model | E1: Vehicle Type | F1: Contract Type | G1: Customer | H1: Sale Type | I1: Address1 | J1: City | K1: State | L1: Zip | M1: PHONE
A2: 1FMUK8KH9SGA60104 | B2: 2025 | C2: FORD | D2: EXPLORER | E2: Truck | F2: Retail | G2: HAYES,DEBORAH | H2: Conventional | I2: 106 GERTRUDE DR | J2: CHALFONT | K2: PA | L2: 18914 | M2: 215-272-2654
A3: 1FMUK8DH1SGA43276 | B3: 2025 | C3: FORD | D3: EXPLORER | E3: Truck | F3: Retail | G3: BASZNIANIN,DARIUSZ | H3: Conventional | I3: 1469 TARLETON PL | J3: WARMINSTER | K3: PA | L3: 18974 | M3: 215-403-1124
A4: 3FMTK3SU8RMA43287 | B4: 2024 | C4: FORD | D4: MUSTME | E4: Truck | F4: Retail | G4: POIRIER,LUC STEPHANE | H4: Conventional | I4: 113 TELEGRAPH RD | J4: PERKASIE | K4: PA | L4: 18944-2644 | M4: 612-434-4486
A5: 1FMCU9MN7RUA78790 | B5: 2024 | C5: FORD | D5: ESCAPE | E5: Truck | F5: Lease | G5: KWIATKOWSKI,GARY | H5: Conventional | I5: 1333 CLEARVIEW DR | J5: JAMISON | K5: PA | L5: 18929-1149 | M5: 215-262-4614
A6: 1FT8W3BN9SEC06449 | B6: 2025 | C6: FORD | D6: F-350 | E6: Truck | F6: Retail | G6: BRAVERMAN,CRAIG BRIAN | H6: Conventional | I6: 410 SCHOOL ST PO BOX 1423 | J6: NORTH WALES | K6: PA | L6: 19454 | M6: 215-275-0011
A7: 2FMPK4J94RBB23644 | B7: 2024 | C7: FORD | D7: EDGE | E7: Truck | F7: Retail | G7: CONVILLE,PATRICK F | H7: Conventional | I7: 1034 WESTON WAY | J7: HATFIELD | K7: PA | L7: 19440-2985 | M7: 215-840-0115
A8: 1FT8W3DM4SEC05536 | B8: 2025 | C8: FORD | D8: F-350 | E8: Truck | F8: Retail | G8: MURPHY IV,WILLIAM HOUSTON | H8: Conventional | I8: 414 GLENWAY RD | J8: GLENSIDE | K8: PA | L8: 19038-7020 | M8: 215-778-9074
A9: 1FMDE7BH1RLB50110 | B9: 2024 | C9: FORD | D9: BRONCO | E9: Truck | F9: Lease | G9: MISCIO,LINDSAY | H9: Conventional | I9: 4959 JULIE COURT | J9: DOYLESTOWN | K9: PA | L9: 18902 | M9: 215-771-4646
A10: 1FMUK8KH7SGA37114 | B10: 2025 | C10: FORD | D10: EXPLORER | E10: Truck | F10: Retail | G10: WAHRHAFTIG,JOEL F | H10: Conventional | I10: 202 SHEPARD LN | J10: CHALFONT | K10: PA | L10: 18914-3569 | M10: 267-475-5561
A11: 1FMUK8DH8SGA36549 | B11: 2025 | C11: FORD | D11: EXPLORER | E11: Truck | F11: Lease | G11: GAMBONE,JOHN MICHAEL | H11: Conventional | I11: 202 RED MAPLE CT | J11: CHALFONT | K11: PA | L11: 18914-4413 | M11: 215-206-6758
A12: 1FMUK8KH9SGB01556 | B12: 2025 | C12: FORD | D12: EXP | E12: Truck | F12: Lease | G12: LOLAS II,WILLIAM | H12: Conventional | I12: 2030 BEDFORDSHIRE RD | J12: FURLONG | K12: PA | L12: 18925 | M12: 215-805-3290
... A295: 1FTBR2C85SKA60181 | B295: 2025 | C295: FORD | D295: TRANSIT | E295: Truck | F295: Retail | G295: PERRIWINKLE INC | H295: Conventional | I295: 1605 W BRISTOL RD | J295: WARMINSTER | K295: PA | L295: 18974-1007 | M295: 267-229-2785
A296: 3FTTW8J98RRB60082 | B296: 2024 | C296: FORD | D296: MAVERICK | E296: Truck | F296: Retail | G296: KOZI GROUP LLC DBA WHITAKER ROOFING AND | H296: Conventional | I296: 1715 W GREEN ST | J296: ALLENTOWN | K296: PA | L296: 18104-4109
A297: 3FTTW8J95RRB72397 | B297: 2024 | C297: FORD | D297: MAVERICK | E297: Truck | F297: Retail | G297: KOZI CONTRACTING LLC | H297: Conventional | I297: 1850 BUTLER ST | J297: EASTON | K297: PA | L297: 18042-4626 | M297: 484-627-1364
A298: 3FTTW8J97RRB81070 | B298: 2024 | C298: FORD | D298: MAVERICK | E298: Truck | F298: Retail | G298: KOZI CONTRACTING LLC | H298: Conventional | I298: 1850 BUTLER ST | J298: EASTON | K298: PA | L298: 18042-4626 | M298: 484-627-1364
A299: 1FTBF2BA8SED47753 | B299: 2025 | C299: FORD | D299: F-250 | E299: Truck | F299: Retail | G299: BIAMONTE,ANTHONY | H299: Conventional | I299: 4096 UPPER MOUNTAIN RD | J299: FURLONG | K299: PA | L299: 18925 | M299: 215-813-2764
A300: 1FMCU0E11SUA46558 | B300: 2025 | C300: FORD | D300: ESCAPE | E300: Truck | F300: Retail | G300: SHUTE,JAMES | H300: Conventional | I300: 3706 JACOB STOUT RD | J300: DOYLESTOWN | K300: PA | L300: 18902-9110 | M300: 215-262-4133
A301: 1FMWK8HC5SGB94144 | B301: 2025 | C301: FORD | D301: EXPLORER | E301: Truck | F301: Retail | G301: ADAIR,JAMES RYAN | H301: Conventional | I301: 5500 JILLIAN WAY | J301: PIPERSVILLE | K301: PA | L301: 18947-1189 | M301: 484-894-5147
A302: 1FMWK8GC1SGB96118 | B302: 2025 | C302: FORD | D302: EXP | E302: Truck | F302: Retail | G302: DALESSIO,REBECKA LEE | H302: Conventional | I302: 1008 TELEGRAPH RD | J302: PERKASIE | K302: PA | L302: 18944-2432 | M302: 215-275-8420
A303: 1FD0W5HN1SED06315 | B303: 2025 | C303: FORD | D303: F-550 | E303: Truck | F303: Retail | G303: A & Y LANDSCAPING & TREE SERVICES, LLC. | H303: Conventional | I303: 3240 BRISTOL RD | J303: CHALFONT | K303: PA | L303: 18914-3443 | M303: 908-616-6468
A304: 1FTFW1L51RKF00322 | B304: 2024 | C304: FORD | D304: F-150 | E304: Truck | F304: Retail | G304: PLUMSTEADVILLE VOLUNTEER FIRE CO. | H304: Fleet | I304: PO BOX 405 | J304: PLUMSTEADVLLE | K304: PA | L304: 18949-0405 | M304: 215-783-6875
A305: 1FMUK8DH0SGA64586 | B305: 2025 | C305: FORD | D305: EXPLORER | E305: Truck | F305: Retail | G305: GREENE,SUZANNE E | H305: Conventional | I305: 323 ROCKY CT W | J305: CHALFONT | K305: PA | L305: 18914 | M305: 203-451-4152
A306: 1FMUK8DH4SGA64235 | B306: 2025 | C306: FORD | D306: EXPLORER | E306: Truck | F306: Retail | G306: MARTIN,DONNA JEAN | H306: Conventional | I306: 1408 MISSION RD | J306: QUAKERTOWN | K306: PA | L306: 18951-5630 | M306: 215-262-3777
A307: 1FMWK8GC6SGC19327 | B307: 2025 | C307: FORD | D307: EXPLORER | E307: Truck | F307: Lease | G307: SISLER,GARY LEE | H307: Conventional | I307: 1067 BRIDGETON HILL RD | J307: UPPR BLCK EDY | K307: PA | L307: 18972-9435 | M307: 267-377-7374
A308: 54DK6S1F3SSA02661 | B308: 2025 | C308: ISUZU | D308: FTR | E308: Truck | F308: Retail | G308: FRED BEANS PARTS INC | H308: Fleet | I308: 131 DOYLE ST | J308: DOYLESTOWN | K308: PA | L308: 18901-3701 | M308: 215-348-0202
... A337: 1FTFW6LDXSFB11763 | B337: 2025 | C337: FORD | D337: F-150 HYBRID | E337: Truck | F337: Lease | G337: MCALISTER,WILLIAM P | H337: Conventional | I337: 7 CASEY CT | J337: NEWTOWN | K337: PA | L337: 18940 | M337: 267-574-4910
A338: 1FTER4LR2SLE20034 | B338: 2025 | C338: FORD | D338: RANGER | E338: Truck | F338: Retail | G338: YOUNG,CHARLES WILLIAM | H338: Conventional | I338: 19 S LINCOLN AVE | J338: NEWTOWN | K338: PA | L338: 18940-2158
A339: 1FTFW7LD4SFB18777 | B339: 2025 | C339: FORD | D339: F-150 HYBRID | E339: Truck | F339: Lease | G339: SANTURNO LLC | H339: Conventional | I339: 810 GREEN ST | J339: LANSDALE | K339: PA | L339: 19446-5221 | M339: 215-692-7067
A340: 1FT6W5L70SWG16229 | B340: 2025 | C340: FORD | D340: F-150 | E340: Truck | F340: Retail | G340: KELER,CYNTHIA A | H340: Conventional | I340: 198 CAFFERTY RD | J340: PIPERSVILLE | K340: PA | L340: 18947-1613 | M340: 610-357-6570
A341: 1FDXE4FN9TDD03135 | B341: 2026 | C341: FORD | D341: E450 | E341: Truck | F341: Retail | G341: PRINCETON UNIVERSITY | H341: Fleet | I341: PO BOX 33 | J341: PRINCETON | K341: NJ | L341: 08543-0033 | M341: 609-258-5033
A342: 3FMCR9BN1SRE60816 | B342: 2025 | C342: FORD | D342: BRONCO SPORT | E342: Truck | F342: Retail | G342: ACKER,PAMELA MARIE | H342: Conventional | I342: 305 NOTTINGHAM PL | J342: CHALFONT | K342: PA | L342: 18914-2454 | M342: 973-204-5392
A343: 3FMCR9CN4SRE54037 | B343: 2025 | C343: FORD | D343: BRONCO SPORT | E343: Truck | F343: Retail | G343: ROLAND,NICHOLAS MICHAEL | H343: Conventional | I343: 333 N BROAD ST APT 1419 | J343: DOYLESTOWN | K343: PA | L343: 18901-3543 | M343: 858-231-0614
A344: 1FTFW5LD0SFB24161 | B344: 2025 | C344: FORD | D344: F-150 HYBRID | E344: Truck | F344: Retail | G344: BALAAM,STEPHEN JOHN | H344: Conventional | I344: 107 BEAUMONT DR | J344: NEWTOWN | K344: PA | L344: 18940-2525 | M344: 267-688-5815
A345: 1FTYE1C8XRKA76919 | B345: 2024 | C345: FORD | D345: TRANSIT | E345: Truck | F345: Retail | G345: TILGHMAN BUILDERS, INC. | H345: Conventional | I345: 263 S YORK RD | J345: HATBORO | K345: PA | L345: 19040-3427 | M345: 267-220-0758
A346: 1FMCU9GN6SUA34698 | B346: 2025 | C346: FORD | D346: ESCAPE | E346: Truck | F346: Retail | G346: EDGAR,FRANK T | H346: Conventional | I346: 1380 SCHOOL HOUSE LN | J346: JAMISON | K346: PA | L346: 18929-1153 | M346: 215-840-1513
A347: 3FMCR9BN8SRE61008 | B347: 2025 | C347: FORD | D347: BRONCO SPORT | E347: Truck | F347: Retail | G347: LYLE,HEATHER LYNN | H347: Conventional | I347: 13 LIBERTY PL | J347: DOYLESTOWN | K347: PA | L347: 18901-2255 | M347: 267-242-5387
A348: 3FMTK4SX9SMA17383 | B348: 2025 | C348: FORD | D348: MUSTME | E348: Truck | F348: Lease | G348: KIRBERGER,STEVEN PAUL | H348: Conventional | I348: 19 FOXTAIL LN | J348: DOYLESTOWN | K348: PA | L348: 18901-2352 | M348: 317-900-2601
A349: 1FTYE1C85RKB22107 | B349: 2024 | C349: FORD | D349: TRANSIT | E349: Truck | F349: Retail | G349: FRED BEANS PARTS INC | H349: Fleet | I349: 131 DOYLE ST | J349: DOYLESTOWN | K349: PA | L349: 18901-3701 | M349: 215-348-0202
A350: 3FTTW8JA7SRA34506 | B350: 2025 | C350: FORD | D350: MAVERICK | E350: Truck | F350: Retail | G350: VEIT,GEORGE FRANCIS | H350: Conventional | I350: 367 STOOPVILLE RD | J350: NEWTOWN | K350: PA | L350: 18940 | M350: 215-375-5017
... A593: 1FBVU4XG3RKB18313 | B593: 2024 | C593: FORD | D593: TRANSIT | E593: Truck | F593: Retail | G593: CLINT & RACHEL ENTERPRISES INC. | H593: Fleet | I593: 445 BUSINESS PARK LN | J593: ALLENTOWN | K593: PA | L593: 18109-9120 | M593: 484-201-0487
A594: 3FTTW8B3XSRB45289 | B594: 2025 | C594: FORD | D594: MAVERICK HYBRID | E594: Truck | F594: Retail | G594: COUNTY OF MONTGOMERY | H594: Fleet | I594: PO BOX 311 | J594: NORRISTOWN | K594: PA | L594: 19404-0311
A595: 3FTTW8B34SRB45451 | B595: 2025 | C595: FORD | D595: MAVERICK HYBRID | E595: Truck | F595: Retail | G595: COUNTY OF MONTGOMERY | H595: Fleet | I595: PO BOX 311 | J595: NORRISTOWN | K595: PA | L595: 19404-0311
A596: 3FTTW8B31SRB45424 | B596: 2025 | C596: FORD | D596: MAVERICK HYBRID | E596: Truck | F596: Retail | G596: COUNTY OF MONTGOMERY | H596: Fleet | I596: PO BOX 311 | J596: NORRISTOWN | K596: PA | L596: 19404-0311
A597: 3FTTW8B32SRB45240 | B597: 2025 | C597: FORD | D597: MAVERICK HYBRID | E597: Truck | F597: Retail | G597: COUNTY OF MONTGOMERY | H597: Fleet | I597: PO BOX 311 | J597: NORRISTOWN | K597: PA | L597: 19404-0311
A598: 1FTEW2LP6SFC00728 | B598: 2025 | C598: FORD | D598: F-150 | E598: Truck | F598: Lease | G598: SPOFFORD,HOWARD MATHEW | H598: Conventional | I598: 1821 PENNLAND CT | J598: LANSDALE | K598: PA | L598: 19446-4333 | M598: 267-640-9693
A599: 1FD8W3FN9SED54543 | B599: 2025 | C599: FORD | D599: F-350 | E599: Truck | F599: Retail | G599: RICHLAND TOWNSHIP WATER AUTHORITY | H599: Fleet | I599: 1328 CALIFORNIA RD STE D | J599: QUAKERTOWN | K599: PA | L599: 18951-4517 | M599: 215-536-9500
A600: 1FMJU1MG4SEA60547 | B600: 2025 | C600: FORD | D600: EXPEDITION | E600: Truck | F600: Retail | G600: LISS,WILLIAM JOHN | H600: Conventional | I600: 143 HULMEVILLE RD | J600: LANGHORNE | K600: PA | L600: 19047-2712 | M600: 215-584-6662
A601: 1FDBF6PG7SKA01274 | B601: 2025 | C601: FORD | D601: TRANSIT | E601: Truck | F601: Retail | G601: FRED BEANS PARTS INC | H601: Fleet | I601: 131 DOYLE ST | J601: DOYLESTOWN | K601: PA | L601: 18901-3701 | M601: 215-348-0202
A602: 1FMDE7BH8SLA99971 | B602: 2025 | C602: FORD | D602: BRONCO | E602: Truck | F602: Lease | G602: JONES,KATIE ANN | H602: Conventional | I602: 1822 AUGUSTA DR | J602: JAMISON | K602: PA | L602: 18929 | M602: 267-750-9533
A603: 3FMTK4SX0SMA51910 | B603: 2025 | C603: FORD | D603: MUSTME | E603: Truck | F603: Retail | G603: CROWE,MATTHEW COOPER | H603: Conventional | I603: 1 JURGENSEN RD | J603: STOCKTON | K603: NJ | L603: 08559 | M603: 206-930-0435
A604: 1FTFW3LD9SFC01467 | B604: 2025 | C604: FORD | D604: F-150 HYBRID | E604: Truck | F604: Retail | G604: GARBER,JENNIFER ELIZABETH | H604: Conventional | I604: 107 WOODBRIDGE CT | J604: SELLERSVILLE | K604: PA | L604: 18960-1975 | M604: 215-828-6963
A605: 3FTTW8JAXSRB43137 | B605: 2025 | C605: FORD | D605: MAVERICK | E605: Truck | F605: Retail | G605: BUCKS COUNTY COMMUNITY COLLEGE | H605: Fleet | I605: 275 SWAMP RD | J605: NEWTOWN | K605: PA | L605: 18940-9677 | M605: 215-968-8390
A606: 1FTFW5LD3SFC01640 | B606: 2025 | C606: FORD | D606: F-150 HYBRID | E606: Truck | F606: Retail | G606: MACDONALD,MEG G | H606: Conventional | I606: 1442 BLUE SCHOOL ROAD | J606: PERKASIE | K606: PA | L606: 18944 | M606: 215-272-7585
A607: 1FT8W2BN2REF90692 | B607: 2024 | C607: FORD | D607: F-250 | E607: Truck | F607: Retail | G607: MACDONALD III,CLETUS JOHN | H607: Conventional | I607: 1442 BLUE SCHOOL RD | J607: PERKASIE | K607: PA | L607: 18944 | M607: 215-778-4744
A608: 3FTTW8B38SRB45422 | B608: 2025 | C608: FORD | D608: MAVERICK HYBRID | E608: Truck | F608: Retail | G608: COUNTY OF MONTGOMERY | H608: Fleet | I608: PO BOX 311 | J608: NORRISTOWN | K608: PA | L608: 19404-0311
A609: 1FMEE4DP6SLB18671 | B609: 2025 | C609: FORD | D609: BRONCO | E609: Truck | F609: Retail | G609: ROSEN,REBECCA L | H609: Conventional | I609: 2054 HOLICONG RD | J609: NEW HOPE | K609: PA | L609: 18938 | M609: 267-885-4684
A610: 1FTFW5L54SFC17726 | B610: 2025 | C610: FORD | D610: F-150 | E610: Truck | F610: Retail | G610: VINCENT POOLS, INC. | H610: Conventional | I610: 1823 DEEP RUN RD | J610: PIPERSVILLE | K610: PA | L610: 18947-9726 | M610: 267-614-0178
A611: 1FMJK1J89SEA68176 | B611: 2025 | C611: FORD | D611: EXPEDITION MAX | E611: Truck | F611: Retail | G611: CLINT & RACHEL ENTERPRISES INC. | H611: Fleet | I611: 445 BUSINESS PARK LN | J611: ALLENTOWN | K611: PA | L611: 18109-9120 | M611: 484-201-0487
A612: 1FT6W5L79SWG21767 | B612: 2025 | C612: FORD | D612: F-150 | E612: Truck | F612: Lease | G612: BRIER,ROBERT M | H612: Conventional | I612: 713 SPRING VALLEY RD | J612: DOYLESTOWN | K612: PA | L612: 18901 | M612: 215-262-7025
A613: 1FMEE8BP8SLB33442 | B613: 2025 | C613: FORD | D613: BRONCO | E613: Truck | F613: Lease | G613: STEINBERG,JESSICA ANNE | H613: Conventional | I613: 301 NOTTINGHAM PL | J613: CHALFONT | K613: PA | L613: 18914 | M613: 610-761-2091
A614: 1FA6P8CF7S5418555 | B614: 2025 | C614: FORD | D614: MUSTANG | E614: Car | F614: Retail | G614: ANDRUKAITIS,ROBERT | H614: Conventional | I614: 3824 TAYLORTOWN RD | J614: FURLONG | K614: PA | L614: 18925-2111 | M614: 561-603-4590
A615: 1FMWK8GC0SGC82097 | B615: 2025 | C615: FORD | D615: EXPLORER | E615: Truck | F615: Retail | G615: PICO,CHRISTOPHER ALAN | H615: Conventional | I615: 129 NETTLES LN | J615: PERKASIE | K615: PA | L615: 18944 | M615: 267-567-3700
A616: 1FTBR1C85SKA83745 | B616: 2025 | C616: FORD | D616: TRANSIT | E616: Truck | F616: Retail | G616: FRED BEANS PARTS INC | H616: Fleet | I616: 131 DOYLE ST | J616: DOYLESTOWN | K616: PA | L616: 18901-3701 | M616: 215-348-0202
A617: 1FTBR1C89SKA77804 | B617: 2025 | C617: FORD | D617: TRANSIT | E617: Truck | F617: Retail | G617: FRED BEANS PARTS INC | H617: Fleet | I617: 131 DOYLE ST | J617: DOYLESTOWN | K617: PA | L617: 18901-3701 | M617: 215-348-0202
A618: 1FMUK8DH1SGD10044 | B618: 2025 | C618: FORD | D618: EXPLORER | E618: Truck | F618: Retail | G618: FRED BEANS FORD | H618: Fleet | I618: 876 N EASTON ROAD | J618: DOYLESTOWN | K618: PA | L618: 18902 | M618: 215-345-7222
A619: 3FMCR9GN3SRF36769 | B619: 2025 | C619: FORD | D619: BRONCO SPORT | E619: Truck | F619: Retail | G619: LAFIURA,MICHAEL FRANK | H619: Conventional | I619: 6069 GERMAN RD | J619: PIPERSVILLE | K619: PA | L619: 18947 | M619: 215-622-0586
A620: 1FMUK8DH9SGC40647 | B620: 2025 | C620: FORD | D620: EXPLORER | E620: Truck | F620: Retail | G620: FRED BEANS FORD | H620: Fleet | I620: 876 N EASTON ROAD | J620: DOYLESTOWN | K620: PA | L620: 18902 | M620: 215-345-7222
... A675: 3FTTW8J9XRRA16095 | B675: 2024 | C675: FORD | D675: MAVERICK | E675: Truck | F675: Retail | G675: DOYLESTOWN TOWNSHIP | H675: Fleet | I675: 425 WELLS RD | J675: DOYLESTOWN | K675: PA | L675: 18901-2717 | M675: 215-416-4317
A676: 1FT8X2BNXREC61610 | B676: 2024 | C676: FORD | D676: F-250 | E676: Truck | F676: Retail | G676: TRAMMEL,LES L | H676: Conventional | I676: 385 OVERLOOK DR | J676: WARMINSTER | K676: PA | L676: 18974
A677: 1FTEW1EP4PKG14709 | B677: 2023 | C677: FORD | D677: F-150 | E677: Truck | F677: Retail | G677: DETAILED ENVIRONMENTS INC | H677: Conventional | I677: 2888 BRISTOL RD | J677: WARRINGTON | K677: PA | L677: 18976 | M677: 215-852-6536
A678: 3FMCR9C62PRD84750 | B678: 2023 | C678: FORD | D678: BRONCO SPORT | E678: Truck | F678: Retail | G678: BETTS,JAMES ROBIN | H678: Conventional | I678: 531 CREEK RD | J678: DOYLESTOWN | K678: PA | L678: 18901 | M678: 215-896-0368
A679: 1FT8W4DM4REC60262 | B679: 2024 | C679: FORD | D679: F-450 | E679: Truck | F679: Retail | G679: LECMAR UNDERGROUND CABLE LLC | H679: Conventional | I679: 1467 N GRAVEL PIKE | J679: PERKIOMENVLLE | K679: PA | L679: 18074-9718 | M679: 267-897-7649
A680: 1FT8W3BA6PED40601 | B680: 2023 | C680: FORD | D680: F-350 | E680: Truck | F680: Retail | G680: BARON,BRET D | H680: Conventional | I680: 5413 POINT PLEASANT PIKE | J680: DOYLESTOWN | K680: PA | L680: 18902 | M680: 267-885-8955
A681: 1FMCU9FN9PUB00749 | B681: 2023 | C681: FORD | D681: ESCAPE | E681: Truck | F681: Retail | G681: BRISTOL TOWNSHIP | H681: Fleet | I681: 2501 BATH ROAD | J681: BRISTOL | K681: PA | L681: 19007-2150 | M681: 267-812-3051
A682: 1FT8W2BN1REC73289 | B682: 2024 | C682: FORD | D682: F-250 | E682: Truck | F682: Retail | G682: STARNAWSKI,RENATA BURA | H682: Conventional | I682: 45A REEDER RD | J682: NEW HOPE | K682: PA | L682: 18938 | M682: 609-851-7680
A683: 1FMCU9MN2RUA02653 | B683: 2024 | C683: FORD | D683: ESCAPE | E683: Truck | F683: Lease | G683: MOLNAR,KAREN DAGMAR | H683: Conventional | I683: 7364 EASTON RD | J683: PIPERSVILLE | K683: PA | L683: 18947 | M683: 732-986-6739
A684: 1FTYE1Y8XPKB97861 | B684: 2023 | C684: FORD | D684: TRANSIT | E684: Truck | F684: Retail | G684: BUCKS COUNTY SPCA | H684: Fleet | I684: 1665 STREET RD | J684: NEW HOPE | K684: PA | L684: 18938 | M684: 267-882-5188
A685: 1FD8X3FN8PEC92833 | B685: 2023 | C685: FORD | D685: F-350 | E685: Truck | F685: Retail | G685: BUCKS COUNTY WATER & SEWER AUTHORITY | H685: Fleet | I685: 1275 ALMSHOUSE RD | J685: WARRINGTON | K685: PA | L685: 18976-1295 | M685: 215-852-3389
A686: 2FMPK4G96RBA14724 | B686: 2024 | C686: FORD | D686: EDGE | E686: Truck | F686: Lease | G686: PAVLOU,MEROPI | H686: Conventional | I686: 3746 SWETLAND DR | J686: DOYLESTOWN | K686: PA | L686: 18902 | M686: 718-926-1350
A687: 1FD8X3FNXPEC92834 | B687: 2023 | C687: FORD | D687: F-350 | E687: Truck | F687: Retail | G687: BUCKS COUNTY WATER & SEWER AUTHORITY | H687: Fleet | I687: 1275 ALMSHOUSE RD | J687: WARRINGTON | K687: PA | L687: 18976-1295 | M687: 215-852-3389
A688: 3FTTW8M38RRA22582 | B688: 2024 | C688: FORD | D688: MAVERICK | E688: Truck | F688: Retail | G688: GLASSMAN,CARL A | H688: Conventional | I688: 33 OLD MILL RD | J688: NEW HOPE | K688: PA | L688: 18938 | M688: 215-862-2570
... A811: 3FTTW8A35RRA32183 | B811: 2024 | C811: FORD | D811: MAVERICK | E811: Truck | F811: Retail | G811: MARTIN WESLEY MACK | H811: Conventional | I811: 216 S 9TH ST | J811: QUAKERTOWN | K811: PA | L811: 18951-1524 | M811: 267-688-7424
A812: 1FTBF4UG9RKA06225 | B812: 2024 | C812: FORD | D812: TRANSIT | E812: Truck | F812: Retail | G812: BUDGET MAINTENANCE INC | H812: Fleet | I812: 135 WALNUT ST | J812: POTTSTOWN | K812: PA | L812: 19464-5420
A813: 1FA6P8TH9R5130192 | B813: 2024 | C813: FORD | D813: MUSTANG | E813: Car | F813: Retail | G813: GOODWIN,CASSANDRA A | H813: Conventional | I813: 275 PARKRIDGE DR | J813: PERKASIE | K813: PA | L813: 18944-1023 | M813: 267-424-5995
A814: 3FMTK4SXXPMA44387 | B814: 2023 | C814: FORD | D814: MUSTME | E814: Truck | F814: Retail | G814: CRESPO,MIGUEL ANGEL | H814: Conventional | I814: 2150 BROOKSHIRE RD | J814: FURLONG | K814: PA | L814: 18925-1253 | M814: 717-885-6188
A815: 1FTFW1P86PKD22618 | B815: 2023 | C815: FORD | D815: F-150 | E815: Truck | F815: Retail | G815: CHALFONT CHEMICAL FIRE ENGINE COMPANY #1 | H815: Conventional | I815: 301 N MAIN ST | J815: CHALFONT | K815: PA | L815: 18914-2740 | M815: 766-8853
A816: 1FT7X2BA1RED47235 | B816: 2024 | C816: FORD | D816: F-250 | E816: Truck | F816: Retail | G816: VERDANT LANDSCAPES, LLC | H816: Conventional | I816: 2934 RIDGE RD | J816: PERKASIE | K816: PA | L816: 18944-3843 | M816: 215-534-6297
A817: 1FMEE5DP3PLB97620 | B817: 2023 | C817: FORD | D817: BRONCO | E817: Truck | F817: Retail | G817: BURKLE,JOSEPH JOHN | H817: Conventional | I817: 3806 BENSALEM BLVD APT 204 | J817: BENSALEM | K817: PA | L817: 19020-4727 | M817: 215-594-1191
A818: 1FT8W2BN8RED47100 | B818: 2024 | C818: FORD | D818: F-250 | E818: Truck | F818: Retail | G818: CONVEYOR SERVICE & INSTALLATION INC | H818: Conventional | I818: 150 BECKYS COR | J818: CHALFONT | K818: PA | L818: 18914-4025 | M818: 215-716-3389
A819: 1FMSK8DH4PGC27075 | B819: 2023 | C819: FORD | D819: EXPLORER | E819: Truck | F819: Lease | G819: FEIERTAG,MEGAN ANNE | H819: Conventional | I819: 749 KING WAY | J819: WARMINSTER | K819: PA | L819: 18974-4347 | M819: 215-760-6336
A820: 1FMJK1J82REA50550 | B820: 2024 | C820: FORD | D820: EXPEDITION MAX | E820: Truck | F820: Lease | G820: BREUER,ALONZETTE P | H820: Conventional | I820: 181 SELLERSVILLE RD | J820: CHALFONT | K820: PA | L820: 18914 | M820: 917-544-6987
A821: 1FTMF1KP1RKD27668 | B821: 2024 | C821: FORD | D821: F-150 | E821: Truck | F821: Retail | G821: PRINCETON UNIVERSITY | H821: Fleet | I821: PO BOX 33 | J821: PRINCETON | K821: NJ | L821: 08543-0033 | M821: 609-258-4025
A822: 1FTYE1Y84RKA20189 | B822: 2024 | C822: FORD | D822: TRANSIT | E822: Truck | F822: Retail | G822: PRINCETON UNIVERSITY | H822: Fleet | I822: PO BOX 33 | J822: PRINCETON | K822: NJ | L822: 08543-0033 | M822: 609-258-4025
A823: 1FTFW1RG6RFA26918 | B823: 2024 | C823: FORD | D823: F-150 | E823: Truck | F823: Retail | G823: MELROSE ENTERPRISES LTD | H823: Conventional | I823: 130 DICKERSON RD | J823: NORTH WALES | K823: PA | L823: 19454-2523 | M823: 215-495-3000
A824: 1FTER4HH0RLE02948 | B824: 2024 | C824: FORD | D824: RANGER | E824: Truck | F824: Retail | G824: WALSH,ROBERT KENNETH | H824: Conventional | I824: 251 KIPLING DR | J824: WARMINSTER | K824: PA | L824: 18974-3919 | M824: 267-317-6898
... A915: 1FTER4KH3RLE29652 | B915: 2024 | C915: FORD | D915: RANGER | E915: Truck | F915: Retail | G915: MAIER JR,JOHN ALONIS | H915: Conventional | I915: 1033 SPRUCE RD | J915: ALLENTOWN | K915: PA | L915: 18106-9408 | M915: 610-442-3128
A916: 1FDWE3FNXRDD23148 | B916: 2024 | C916: FORD | D916: E350 | E916: Truck | F916: Retail | G916: PAPPAGEORGE CONSTRUCTION SERVICE LLC | H916: Conventional | I916: 901 LIMEKILN RD | J916: DOYLESTOWN | K916: PA | L916: 18901
A917: 1FMSK8DH2RGA46236 | B917: 2024 | C917: FORD | D917: EXPLORER | E917: Truck | F917: Lease | G917: BOWMAN,BRIAN JOHN | H917: Conventional | I917: 42 HICKORY LN | J917: CHALFONT | K917: PA | L917: 18914-2013 | M917: 215-313-1786
A918: 1FMCU9J95HUD81279 | B918: 2017 | C918: FORD | D918: ESCAPE | E918: Truck | F918: Retail | G918: ATKINS,RENEE J | H918: Conventional | I918: 109 N 3RD ST | J918: NORTH WALES | K918: PA | L918: 19454-3106 | M918: 215-499-0720
...
